Workbook

Sheet Матрица
A1: Что это | E1: Сейчас (прототип) | J1: MVP — 8 000 абонентов | P1: Тираж — 90 000 абонентов
A2: № | B2: Тип | C2: Контейнер / связь | D2: Какие контейнеры затрагивает | E2: Технология и стек (что именно используется) | F2: Как реализовано сейчас | G2: С чем сравнивали и почему выбрано | H2: Где сравнение (документ, раздел) | I2: Проблемы | J2: Что будет | K2: Стек | L2: Почему | M2: Доработки, чел-дн (мин) | N2: Доработки, чел-дн (макс) | O2: Основа оценки | P2: Что будет | Q2: Стек | R2: Почему | S2: Доработки, чел-дн (мин) | T2: Доработки, чел-дн (макс) | U2: Основа оценки | V2: Источники
A3: 1 | B3: Контейнер | C3: AI-виджет (интерфейс абонента) | D3: AI-виджет; Backend (на прототипе отдаёт статику виджета) | E3: HTML + JavaScript без фреймворка и сборки + CSS (каталог `web/`); поток ответа — fetch и чтение SSE | F3: Три статических файла: HTML / JS / CSS (`web/`), отдаются самим Backend; ответ приходит потоком (SSE). Оформлен как личный кабинет. | G3: React/TS (целевой) на прототипе отклонён: ничего архитектурного не проверил бы, но потребовал бы второго процесса на демонстрации. | H3: ADR-200, раздел «Сравнение вариантов по слоям», подраздел «Интерфейс абонента: виджет» | I3: Это демо-стенд, а не продукт. Нет настоящей SSO: абонент выбирается из справочника, идентификатор берётся из метаданных запроса. | J3: Виджет, встроенный в личный кабинет, с SSO-сессией. | K3: React / TypeScript, сборка в образ `ai-widget`, за Ingress (nginx). | L3: Встраивание в существующий ЛК; целевая схема развёртывания (`C4_Deployment`). | M3: 10 | N3: 15 | O3: Оценка автора | P3: Без изменений | V3: ADR-100; C4_L3_Widget; C4_Deployment
A4: 2 | B4: Контейнер | C4: Backend (API, классификация, поиск, сборка ответа) | D4: Backend | E4: Python 3.12; FastAPI; uvicorn; pydantic v2; httpx; контейнер docker (multi-stage) | F4: Python 3.12 + веб-фреймворк FastAPI + сервер запуска uvicorn (ASGI: принимает HTTP-запросы и вызывает код FastAPI). В контейнере (multi-stage `Dockerfile`), поднимается `docker compose up`. Внутри: Triage, поиск по базе знаний, шесть путей ответа, FSM. | G4: Язык: Go и Node.js — отклонены: нет зрелого RAG/PII-инструментария (LiteLLM, sentence-transformers, Presidio живут в Python), а RAG-логика обязана быть внутри одного контейнера; выигрыш Go в конкурентности не нужен, узкое место — задержка внешней модели. Фреймворк: FastAPI выбран против Flask, Django REST Framework и Litestar — родные async и потоковый ответ, pydantic-схемы и OpenAPI из тех же моделей, лёгкий вес; Flask и DRF дублируют описание моделей и требуют расширений, Litestar не даёт выигрыша при меньшем сообществе. Сервер: uvicorn выбран против Hypercorn, Daphne, Granian и gunicorn — стандартный сервер FastAPI, минимум настроек; остальным нечего добавить проекту (внешний трафик и TLS закрывает Ingress, скорость Rust-ядра не нужна, менеджер процессов заменяет Kubernetes). Подробно — ADR-200. | H4: ADR-200: «Почему Python, а не Go или Node.js», «Почему FastAPI, а не другой Python-фреймворк», «Почему uvicorn» | I4: Проверка «идентификатор абонента принадлежит сессии» на шагах записи спроектирована, но не реализована (открытый P1). В compose включён режим разработки (`--reload`, подключённые каталоги). | J4: Те же контейнеры в Kubernetes, несколько реплик; проверка привязки абонента к сессии на каждом шаге записи; продовый режим запуска. | K4: Python / FastAPI, uvicorn без режима перезагрузки и без подключённых каталогов; Deployment в Kubernetes, секреты из Kubernetes Secret (GitLab CI variables). | L4: Без привязки сессии запись от имени абонента включать нельзя (риск подмены, ADR-400). | M4: 3 | N4: 4 | O4: Из блока ADR-600: Основная разработка Этапа 2 | P4: Без изменений | V4: ADR-200; ADR-400; ADR-600
A5: 3 | B5: Контейнер | C5: Классификатор обращений (Triage) | D5: Backend (модуль Triage); embedding-inference (эмбеддер для запасного k-NN) | E5: Python: регулярные выражения `re` и словарь ключевых слов; запасной k-NN — sentence-transformers, multilingual-e5-small (CPU), косинусная близость | F5: Python, без модели на основном пути. Тема (путь ответа): подстроки и регулярные выражения — `TOPIC_MARKERS`, `TARIFF_PATTERNS`, `WATER_QUALITY_PATTERNS`, `TEMPLATE_PATTERNS`, `ACCOUNT_PATTERNS` в `app/agents/triage.py`. Тип обращения (регистрация): словарь ключевых слов `KEYWORDS` в `app/taxonomy.py`, слова взяты из 136 настоящих обращений (на отложенной трети выборки охват 75%, точность 65%; выборка мала). Когда правила молчат — запасной k-NN по эмбеддингам (косинусная близость к размеченным примерам `EXAMPLES` в `app/agents/topic_fallback.py` и `app/agents/inquiry_type_fallback.py`); эмбеддер — `multilingual-e5-small` на CPU, тот же, что у поиска (вторая модель не грузится). Запасной классификатор типа знает 7 из 16 типов. Все правила и слова по каждому типу и теме, их проработка и этап сведены в таблице `Inquiry_Types.xlsx`. | G5: Отдельный вызов LLM на каждый запрос отклонён: стоимость и задержка ради задачи, которую решают правила. k-NN переиспользует уже загруженный эмбеддер, вторая модель не нужна. | H5: ADR-300, раздел 1 «Классификация» (правила / LLM-классификатор / k-NN); слова и статистика — Inquiry_Types.xlsx | I5: 9 типов из 16 запасной классификатор не знает: refund, debt, payment, penalty, accrual_recalculation, inquiry_cancellation, meter_reacceptance, meter_reacceptance_auto, other. По ним работают только ключевые слова. Реальные тексты по этим типам — споры, а не заявки, нужен размеченный корпус вопросов-заявок (его пока нет). Пороги k-NN подобраны замером на e5-small и не переносятся на другую модель. Классификация даёт одну тему и один тип на реплику; несколько задач в реплике разбирает детектор намерений (`app/agents/intents.py`, реализован на прототипе). Замер: 31 из 136 настоящих обращений (23%) подходят под несколько типов по ключевым словам — это пересечение слов; детектор на тех же текстах находит несколько задач в 1 из 136 (0,7%). Доля по разметке людьми не измерена — при доле выше 5% агент переводится на LangGraph (триггер 4, ADR-200). | J5: Сначала анализ всех типов на живых обращениях (строка «Анализ всех типов…» ниже), затем заново собранная таблица типов; расширение запасного классификатора на оставшиеся девять типов; устранение найденных ложных срабатываний; пересчёт порогов k-NN под новую модель эмбеддингов. | K5: Правила и словарь — как сейчас; k-NN на эмбеддере поиска (предварительно BGE-M3, GPU); пороги подбираются заново, окончательная модель — по итогам анализа на живых обращениях. | L5: Чтобы обращения по всем типам справочника регистрировались автоматически. Пороги надо подбирать заново: их величина — свойство пары «модель + примеры». Оценка в этой строке — только расширение классификатора и подбор порогов: 1,5–2,5 недели после появления размеченного корпуса (ADR-600). Анализ на живых данных и пересборка таблицы — 13–19 чел-дн в строке «Анализ всех типов…»; вместе с ним работа над классификатором — 23–34 чел-дн. | M5: 8 | N5: 12 | O5: Из блока ADR-600: Качество поиска и классификации | P5: Как на MVP (изменений нет). | Q5: Те же правила; k-NN на эмбеддере поиска (модель — по решению для MVP и тиража). | R5: Собственная модель генерации на тираже классификацию не затрагивает: k-NN использует эмбеддер поиска. | V5: ADR-300; ADR-600; Inquiry_Types.xlsx
A6: 4 | B6: Контейнер | C6: LLM Gateway (лимиты → PII → модель → проверка) | D6: LLM Gateway (сейчас внутри Backend); Redis (лимиты); LLM Provider; Postgres (события использования) | E6: Python; LiteLLM (Router); Redis; Presidio + spaCy (обезличивание); prometheus-client; PostgreSQL | F6: Python-модуль внутри контейнера Backend (`app/gateway/`), работает по цепочке: лимиты запросов (Redis) → обезличивание (Presidio + русская модель spaCy + собственные распознаватели) → вызов модели через LiteLLM → проверка ответа на потоке (регулярные выражения) → запись события использования (Postgres) и метрики (prometheus-client). LiteLLM подключён библиотекой (`Router`) внутри процесса по конфигурации `litellm_config.yaml`: единый OpenAI-совместимый интерфейс, повторы и переключение на запасного провайдера при сбое; YandexGPT вызывается через OpenAI-совместимый адрес. К шлюзу ходит только Backend. | G6: Свой клиент на каждого провайдера отклонён: дублирование ради контроля, который LiteLLM уже даёт (по документации библиотеки: 100+ адаптеров, единый интерфейс; в проекте настроены повторы и цепочки запасных, circuit breaker не настроен; переключение на запасного сработало на живом трафике — шесть вызовов ушли на локальную модель при пустом ключе). Отдельный прокси-сервер LiteLLM на прототипе не взят: это второй процесс со своим портом и конфигурацией, память отдельного процесса LiteLLM не измерялась (на машине 15 ГБ, контейнер Backend занимает 1,32 ГиБ); библиотека принимает тот же список моделей и цепочки запасных провайдеров, формат файла совместим с прокси. Смена провайдера — правка переменной `LLM_PROVIDER`, код не меняется: это условие ADR-200 (минимум два провайдера с автопереключением). Весь нужный инструментарий (LiteLLM, Presidio, sentence-transformers) существует в Python — тот же язык, что у Backend. Зарубежные провайдеры исключены: 152-ФЗ. | H6: ADR-200, раздел «LLM-хостинг»: таблица стратегии и шлюза, подраздел «Как устроен шлюз к модели» | I6: Отдельного контейнера нет — шлюз пока внутри Backend. GigaChat на прототипе недоступен (нужны сертификаты НУЦ), поэтому целевой основной провайдер MVP на машине прототипа не проверен. Проверки ответа — регулярные выражения; тонкие случаи (тон, обоснованность) ловятся слабо, обоснованность оценивает отдельный судья. | J6: Отдельный контейнер `llm-gateway`; через него ходят и Backend, и агент записи. | K6: Python / LiteLLM (Router или прокси — решается при выносе; формат конфигурации совместим), отдельный Deployment; Redis для лимитов; Presidio; события использования — в Postgres; GigaChat Pro основной, YandexGPT резерв. | L6: Единый обязательный путь для всех потребителей: обхода обезличивания на Этапе 2 быть не должно. | M6: 3 | N6: 5 | O6: Оценка автора | P6: Без изменений | V6: ADR-200; C4_L3_LLM
A7: 5 | B7: Контейнер | C7: PII Filter (обезличивание) | D7: LLM Gateway (Backend) | E7: Python; Presidio (analyzer, anonymizer); spaCy ru_core_news_md; собственные распознаватели СНИЛС, ИНН, лицевого счёта, телефона, email | F7: Presidio + собственные распознаватели (СНИЛС и ИНН с контрольными суммами, лицевой счёт, телефон, email), русская модель spaCy. Стоит в шлюзе до обращения к провайдеру. | G7: Presidio + собственные распознаватели выбраны против «только регулярных выражений» (не находят ФИО), русского NER вроде Natasha (по документации — имена и адреса, но не СНИЛС, ИНН, лицевой счёт, телефон, почту; не проверялась) и внешнего сервиса (данные уходят за периметр, запрещено). Базовый набор Presidio один не годился: лицевой счёт определялся как телефон, одна почта получала три метки. | H7: ADR-400, раздел «Сравнение вариантов по слоям безопасности», подраздел «Почему Presidio и собственные распознаватели»; подраздел «Модель разбора языка для обезличивания: что будет сравниваться» | I7: Эмбеддинг запроса минует фильтр, поэтому онлайн-эмбеддинги допустимы только локальные (внешний API для запроса запрещён). | J7: Проверка полноты обезличивания на размеченных живых обращениях (ФИО, адрес, телефон, лицевой счёт, почта): сколько ПДн пропущено; сравнение моделей разбора языка (spaCy md / sm / lg, Natasha); правка распознавателей. | K7: Presidio + spaCy (модель выбирается по замеру) + собственные распознаватели; скрипты замера полноты и точности. | L7: Для 152-ФЗ пропуск ПДн опаснее ложной находки, а полнота на живых данных не измерялась: измерены только ложные находки на 136 обращениях. | M7: 4 | N7: 6 | O7: Из блока ADR-600: Качество поиска и классификации | P7: Без изменений | V7: ADR-400; ADR-600
A8: 6 | B8: Контейнер | C8: Guardrails и судья качества | D8: LLM Gateway (проверки на потоке); Backend (фоновая оценка); Ollama (локальная модель судьи на прототипе) | E8: Python: регулярные выражения для проверок на потоке; судья — LiteLLM → Qwen2.5-7B через Ollama (прототип), YandexGPT (MVP) | F8: Назначение: проверить ответ модели до показа абоненту — персональные данные, недопустимый тон, разглашение внутренних инструкций. Синхронно (бюджет 50 мс; замер 24.09.2026: на ответе ≈800 знаков P95 ≈49 мс, на ≈2 000 знаков P95 ≈120 мс — на длинных ответах бюджет не держится, проверяется весь накопленный текст): ПДн в ответе, тон, разглашение промпта, ложное «сделал» (модель пишет, что выполнила операцию) — при нарушении поток обрывается. Асинхронно: судья обоснованности (локальная Qwen2.5-7B через Ollama), не блокирует выдачу. | G8: Проверки на потоке — регулярные выражения (бюджет менее 50 мс на кусок; ML-модель токсичности не измерялась (на CPU есть риск), LLM-судья работает секундами — у YandexGPT первый кусок приходит за 0,3–21 с (19 вызовов), внешний сервис уносит данные за периметр). Судья не может совпадать с отвечающей моделью: при совпадении оценка пропускается и это фиксируется. | H8: ADR-300, раздел 5 «Судья качества ответа» и подраздел «Судья качества: какие модели и что будет сравниваться»; ADR-400, раздел «Сравнение вариантов по слоям безопасности», подраздел «Почему проверки ответа — регулярные выражения на потоке» (проверки на потоке) | I8: Проверки на потоке подобраны без живых ответов модели: частота ложных блокировок и пропусков неизвестна. Судья слабый, оценка предварительная (provisional): пороги качества не откалиброваны на размеченном наборе. Ложное «сделал» ловится правилом `unperformed_action` (начало предложения с глаголом первого лица) и правилом в промпте; до них модель отвечала «Передал показания 1234. Проверил наличие долга — его нет». Перечень глаголов собран вручную, частота ложных блокировок и пропусков на живых ответах неизвестна. | J8: Судья на другом провайдере, чем отвечающая модель; тест нескольких моделей судьи (Qwen2.5-7B, Qwen2.5-14B/32B, YandexGPT, GigaChat Pro) против ручной разметки 100–200 живых ответов; калибровка порогов (6–9 чел-дн). Проверка работоспособности проверок на живых данных (ложные блокировки, пропуски ПДн, тона и разглашения промпта) — в строке «Проверка на живых данных: Guardrails и выбор провайдера» ниже. | K8: Судья — YandexGPT при отвечающем GigaChat Pro или наоборот (по решению об основном провайдере); выбор модели судьи — по замеру согласия с человеком. | L8: Независимость оценки обеспечена конструктивно, а не договорённостью. | M8: 6 | N8: 9 | O8: Из блока ADR-600: Качество поиска и классификации | P8: Без изменений | V8: ADR-300; C4_L3_LLM
A9: 7 | B9: Контейнер | C9: LLM Provider (генерация ответа) | D9: LLM Gateway; внешний LLM Provider (YandexGPT / GigaChat); Ollama (тесты) | E9: YandexGPT Pro (управляемый API, РФ); LiteLLM; Qwen2.5-7B через Ollama для тестов | F9: YandexGPT Pro — управляемый API в РФ. Для тестов локально Qwen2.5-7B (Ollama). Время до первого куска по 19 вызовам: медиана 0,78 с, P90 5,6 с, максимум 21,7 с (ориентир 0,5 с не достигнут); до конца ответа — медиана 2,6 с. | G9: GigaChat технически недоступен на машине прототипа (нужны корневые сертификаты НУЦ; отключать проверку TLS недопустимо). Зарубежные провайдеры отклонены на всех этапах: 152-ФЗ. Собственная модель тиража: Qwen2.5-32B выбран против Llama 3.x и открытых весов GigaChat — лицензия Apache 2.0, сильный русский среди открытых моделей, одно семейство 7B (уже используется для тестов) → 32B без переделки, 32B в INT4 помещается на одну карту A100 (в проекте заложено 34 ГБ весов плюс запас под кэш; на GPU не проверялось, а для INT4 по общим сведениям ожидается около 17–20 ГБ — 34 ГБ скорее соответствуют 8-битному представлению). Выбор сделан по репутации модели, на своём эталонном наборе не проверен; прогон запланирован при переходе к тиражу (3–5 чел-дн, ADR-600). | H9: ADR-300, раздел 4 «Генерация ответа абоненту» и подраздел «Сравнение семейства self-hosted-модели»; стоимость — ADR-500 | I9: Ни YandexGPT, ни GigaChat не проверены на живых вопросах абонентов; GigaChat на прототипе недоступен. Качество ответов не измерено на собственном эталонном наборе; выбор модели по репутации. | J9: GigaChat Pro как основная, YandexGPT как резерв с автопереключением — предварительно: оба провайдера проверяются на ограниченном объёме живых вопросов, после чего принимается решение об основном и запасном (строка «Проверка на живых данных…» ниже). | K9: Управляемые API в РФ через LLM Gateway. | L9: Ранее выбран основным по совокупности; резерв защищает от отказа провайдера. | M9: 3 | N9: 5 | O9: Оценка автора | P9: Собственная модель в закрытом контуре, внешние API остаются до срабатывания триггера. | Q9: Qwen2.5-32B INT4, vLLM, 1× GPU A100 80 ГБ. | R9: Включается по триггеру (нагрузка, требование ИБ отказаться от внешних API, падение SLA провайдера), не по дате. Одна карта с запасом покрывает пик 3,4–6,75 запроса. | S9: 5 | T9: 10 | U9: ADR-600 | V9: ADR-300; ADR-500; ADR-600
A10: 8 | B10: Контейнер | C10: Эмбеддинги (модель поиска) | D10: Backend (поиск); embedding-inference (MVP); ETL индексации; Qdrant; Triage (запасной k-NN) | E10: sentence-transformers; multilingual-e5-small (CPU) на прототипе; BGE-M3 (GPU) на MVP | F10: `multilingual-e5-small` на CPU: 0,46 ГБ, 22–37 мс на запрос (замеры 24.09.2026) — укладывается в бюджет 100 мс с запасом ≈3–4,5 раза. Стек: библиотека sentence-transformers (`SentenceTransformerEmbedder`, `app/kb/search.py`); модель задаётся параметром `embedding_model` (`app/config.py`); тот же эмбеддер использует запасной классификатор Triage. | G10: Сравнение моделей проведено в ADR-300, раздел 2 (задержка и размер — замер `scripts/measure_search_models.py`); замер поиска на прототипе — `golden_set/measurement.json` (e5-small: 20 из 20 на вопросах корпуса, 12 из 30 на первом месте и 23 из 30 в первой тройке на живых формулировках). Почему BGE-M3 для MVP: многоязычная, длинные тексты, общий каркас с реранкером BGE-reranker-v2-m3 — это свойства модели, а не замер на своих данных; подробно и с перечнем кандидатов — ADR-300, «Почему BGE-M3 — кандидат для MVP и что будет сравниваться». Кандидаты: BGE-M3: 2,14 ГиБ (fp32; прежние 4,25 ГБ — две копии весов в кэше), 210–300 мс на CPU (в 2–3 раза выше бюджета; на GPU не измерялась), качество на русском не проверено на эталонном наборе. GigaChat Embeddings — только для офлайн-индексации: запрос минует обезличивание. | H10: ADR-300, раздел 2 «Эмбеддинги» и подраздел «Почему BGE-M3 — кандидат для MVP и что будет сравниваться»; замер поиска — golden_set/measurement.json; скрипт замера — scripts/measure_search_models.py | I10: Смена модели — самое дорогое решение для отмены: версия хранится в каждом векторе, смена = полная переиндексация. Сравнение e5-small и BGE-M3 по качеству не проведено. | J10: В кластере владельца GPU нет: на MVP — e5-small на CPU (36–37 мс на запрос, замер); BGE-M3 на GPU — только если владелец после проверки на реальных данных решит добавить GPU-узел (строка «GPU-узел в кластере владельца»); сами тесты BGE-M3 идут офлайн на CPU. Модель выбирается по тесту 4–5 моделей (e5-small, e5-large, BGE-M3, модели, дообученные на русском) на размеченном наборе из живых обращений; пороги подбираются под каждую модель (ADR-600, «Тест моделей эмбеддингов для MVP»). Размеченный набор берётся из строки «Анализ всех типов…». | K10: Без GPU: sentence-transformers, e5-small на CPU (2 реплики). С GPU-узлом: BGE-M3, сервис `embedding-inference`. | L10: Многоязычная модель, по репутации лучше на русском; решение принимается один раз на этап после замера на эталонном наборе. | M10: 10 | N10: 14 | O10: Из блока ADR-600: Качество поиска и классификации | P10: Как на MVP (изменений нет). | Q10: BGE-M3 на том же GPU-пуле. | R10: Модель поиска не зависит от того, чья модель генерирует ответ; карта A100 на тираже нужна только генерации. Модель для тиража подтверждается повторным решением по живой статистике MVP. | V10: ADR-300; ADR-500
A11: 9 | B11: Контейнер | C11: Реранкер (переранжирование топ-20 → топ-3) | D11: Backend (поиск); reranker-inference (MVP); ETL индексации (офлайн-роль) | E11: sentence-transformers (кросс-энкодер); BAAI/bge-reranker-v2-m3; на прототипе выключен | F11: Реализован и проверен, но выключен (`RERANKER_ENABLED=false`): кросс-энкодер BGE-reranker-v2-m3 на CPU считает 5,8–25 с (последний замер 24.09.2026 — 7,2 с) при бюджете 100 мс; на GPU не измерялся. | G11: Поиск без переранжирования (топ-3 сразу из косинуса) — единственный вариант на CPU. BGE-reranker-v2-m3 выбран как целевой: многоязычный, из того же семейства, что BGE-M3, и проверен на 30 живых формулировках (первое место у 21 из 30 вместо 7, MRR 0,79 вместо 0,52) — но замер устарел: сделан на корпусе из 20 фрагментов, где топ-20 — весь корпус; на текущем индексе косинус даёт 12 из 30, выигрыш реранкера над ним не измерялся, а на 30–100 тыс. векторов MVP зависит от полноты первой ступени. Другие реранкеры (jina-reranker-v2, mMiniLM, bge-reranker-v2-gemma) не измерялись. | H11: ADR-300, раздел 3 «Переранжирование» и подраздел «Почему BGE-reranker-v2-m3 — кандидат для MVP и что будет сравниваться»; офлайн-роль — там же, подраздел «Офлайн-роль при индексации: отсев дублей (не решено)»; замер — golden_set/reranking.json | I11: Онлайн-роль зависит от GPU. Офлайн-роль (выбор представительного чанка среди дублей) в коде не реализована и не подтверждена: модель обучена на паре «запрос — документ», а запроса при индексации нет. Отдельной офлайн-модели не выбрано: на схеме ETL указана та же BGE-reranker-v2-m3 (блок «Reranker Client (offline)» после блока «Quality & Dedup Filter»: MinHash/SimHash, Жаккар ≥ 0,9, quality_score). Расчёт по замеру: 7,2 с на 20 кандидатов ≈ 0,36 с на пару, за окно 3 ч ≈ 30 000 пар; на паре «фрагмент — фрагмент» время не измерялось. Варианты отсева: quality_score, центроид, кросс-энкодер, косинусный порог (ADR-300, раздел 3); доля дублей в корпусе не измерялась. | J11: Без GPU-узла остаётся выключенным (на CPU 7,2 с при бюджете 100 мс); включается только если владелец после проверки на реальных данных решит купить GPU-узел. Порядок теста (24.09.2026): (1) базовая линия качества ответов без реранкера на реальных данных — не менее 200 обращений, оценка эксперта (1,5–2 чел-дн); (2) разбор ошибок: верного фрагмента нет в топ-20 / есть в топ-20, но не в топ-3 (реранкер может исправить только их) / ошибка генерации (1–2 чел-дн); (3) тест 2–3 реранкеров офлайн на CPU на тех же вопросах, оценка изменившихся ответов (2–4 чел-дн); (4) решение о GPU: реранкер включается и GPU арендуется, только если без реранкера не проходят пороги А и Б, а реранкер их исправляет. Порог пустых выдач (критерий В): не более 3% вопросов с ответом, пустых из-за порядка; рабочее значение автора. Порядок в коде: кандидаты по косинусу → реранкер → первые три → отсев по косинусному порогу 0,872; реранкер может поднять наверх фрагменты с низким косинусом, они отсекутся, выдача станет неполной или пустой — не измерялось. В тесте сравниваются порядки «реранкер → порог» и «порог → реранкер» по hit@1, hit@3, MRR и доле пустых выдач (считается по каждому вопросу на одних и тех же 20 кандидатах: пустая выдача; меньше трёх; пустая из-за порядка — пуста при «реранкер → порог», но не пуста без реранкера; верный фрагмент отсечён порогом; условный пример на 10 вопросах — в ADR-600; у порядка «порог → реранкер» пустых из-за порядка по построению нет; вопросы без ответа в базе размечаются отдельно и считаются отдельно) (в пределах шагов 4–5, оценка автора; правка порядка в коде, если понадобится, ≈0,5 чел-дн внутри оценки). Добавлено 3–5 чел-дн к прежним 5–7 (оценка автора). Единая выборка 300–400 обращений для эмбеддингов, реранкера и проверки провайдеров; ответы генерируются один раз в блоке проверки провайдеров (он идёт раньше), здесь оценивается только качество; если выборки разные — +0,5–1 чел-дн, вне итога. Время эксперта водоканала (не чел-дн команды): 29–52 ч ≈ 4–6,5 рабочих дня — верный фрагмент базы или пометка «ответа в базе нет» для 300–400 обращений 15–33 ч, оценка 200 ответов 10–13 ч, оценка изменившихся ответов 3–4 ч, подтверждение порогов 1–2 ч (оценка автора); наличие эксперта неизвестно. Замер офлайн-роли (2–3 чел-дн): доля кластеров дублей на реальных документах, четыре способа выбора представителя (quality_score, центроид, кросс-энкодер, косинусный порог), проверка экспертом, что нужный текст не потерян; при неподтверждении кросс-энкодера офлайн-роль снимается, отсев строится на остальных способах; состав работы — предложение автора от 25.09.2026, порог «заметно лучше» не определён. Тест 2–3 моделей реранкера на размеченном наборе с порогом под каждую (8–12 чел-дн вместе с базовой линией ответов и разбором ошибок, см. порядок ниже); первым шагом — повторный замер базовой линии на текущем индексе, прежний сделан на корпусе из 20 фрагментов — после выбора модели эмбеддингов. | K11: Без GPU: выключен. С GPU-узлом: BGE-reranker-v2-m3, сервис `reranker-inference`. | L11: Уточнение выдачи; на GPU укладывается в бюджет задержки. | M11: 10 | N11: 15 | O11: Из блока ADR-600: Качество поиска и классификации | P11: Без изменений | V11: ADR-300; C3/C4_L3_ETL_RAG_1
A12: 10 | B12: Контейнер | C12: Векторная база (Qdrant) | D12: Qdrant; Backend (читает); ETL индексации (пишет) | E12: Qdrant (docker `qdrant/qdrant`); клиент qdrant-client; индекс HNSW (m=16, ef=128); payload-индексы; blue-green алиасы коллекций | F12: Qdrant в `docker compose`; в коде по умолчанию корпус в памяти. Есть фильтр по типу обращения и переключение индекса без остановки поиска (blue-green алиас). | G12: Объём заложен: несколько тысяч документов (3 000–5 000) × 10–20 частей на документ (допущение) = 30 000–100 000 векторов размерности 1 024 (BGE-M3), 123–410 МБ. Замер Qdrant на 100 000 случайных векторов: 477 МБ на диске, ОЗУ 527 МиБ; P50 27,5 мс / P99 64,9 мс без фильтра, 14,3 / 36,8 мс с фильтром по типу — в бюджете 100 мс. pgvector не отклонён по качеству: на этом объёме рабочая альтернатива (не измерялась), Qdrant выбран из-за алиасов коллекций (blue-green уже в коде) и отдельной нагрузки от основной базы. Milvus и OpenSearch — по документации, не измерялись. | H12: ADR-200, раздел «Сравнение вариантов по слоям», подраздел «Почему Qdrant, а не другая векторная база» (и строка «Векторный поиск (целевое)» в таблице «Хранилища») | I12: Образ в compose не привязан к версии (`latest`) — для продакшена версию надо зафиксировать. | J12: Qdrant self-hosted в Kubernetes на быстром диске, с резервным копированием. | K12: Qdrant, StatefulSet + PVC на NVMe. | L12: Целевое хранилище векторов; миграция — смена конфигурации, код уже проверен на реальном сервере. | M12: 3 | N12: 5 | O12: Оценка автора | P12: Без изменений | V12: ADR-200; ADR-100
A13: 11 | B13: Контейнер | C13: Данные абонента (чтение из Биллинга и Диспетчерской) | D13: Backend (читает); Биллинг и Диспетчерская (источники, внешние); Redis (кэш — только после замера) | E13: Прототип: словари в памяти процесса из CSV. MVP: клиенты XML-RPC (Биллинг) и REST (Диспетчерская) в Backend, параллельные вызовы, таймауты и повторы; без Postgres-представления; кэш Redis — по итогам замера | F13: Пример Биллинга и ЛК (200 счетов, 203 счётчика, 1323 начисления) читается из CSV при старте в словари в памяти процесса (`app/billing/source.py`). Postgres и Redis для данных абонента на прототипе не используются. Источник стоит за интерфейсом, на MVP его заменяет клиент к настоящим API (оценка автора, не проверялось). | G13: Заказчик проекта 25.09.2026: данные абонента нужны онлайн из систем. Поэтому основной путь — чтение из Биллинга (XML-RPC) и Диспетчерской (REST) на каждый вопрос; вызовы параллельные, только за нужными данными; при отказе системы — ответ «данных сейчас нет», без подстановки старых. Отклонены: слепок в памяти (данные не обновляются, у реплик разный возраст), предрасчёт по расписанию в материализованном представлении Postgres (был в плане; данные отстают на период пересчёта), Feature Store (Feast/Tecton — избыточен и свежесть не решает). Кэш Redis с коротким сроком жизни — только после замера: включается, если время вызова API не укладывается в бюджет ответа либо лимиты владельца ниже нагрузки. Задержка и лимиты API не измерялись (доступа нет). Сравнение по требованиям и документации, не по пробному внедрению. | H13: ADR-200, раздел «Сравнение вариантов по слоям», подраздел «Данные абонента: читаем из систем в момент вопроса, кэш — после замера»; замер — ADR-600, «Замер чтения данных абонента из систем» | I13: Скорость, лимиты и доступность API Биллинга и Диспетчерской неизвестны, доступа к ним нет; задержка ответа теперь зависит от чужих систем. Доля вопросов, которым нужны данные абонента, не измерена. Нагрузка на системы владельца пропорциональна числу вопросов: до 0,058 вызова/с на MVP и 0,656 на тираже в максимуме прогноза (верхняя оценка — один вызов на вопрос). | J13: Чтение из Биллинга и Диспетчерской в момент вопроса; таймауты, повторы и ответ «данных сейчас нет» при отказе системы; замер времени вызовов и лимитов API (ADR-600, «Замер чтения данных абонента из систем»); кэш Redis — по итогам замера. Сами клиенты API — в строках «Backend ↔ Биллинг» и «Backend ↔ Диспетчерская». | K13: Клиенты XML-RPC и REST в Backend, параллельные вызовы (asyncio), таймауты и повторы. Без Postgres-представления и без задания по расписанию. Redis со сроком жизни в минуты — только по итогам замера. | L13: Данные абонента (баланс, начисления, показания, заявки) меняются; ответ по предрасчитанной сводке может оказаться неверным (требование заказчика 25.09.2026). | M13: 2.5 | N13: 4 | O13: Оценка автора; замер API — ADR-600 | P13: Без изменений | V13: ADR-200; ADR-600
A14: 12 | B14: Контейнер | C14: Redis (квоты, состояние диалога) | D14: Redis; LLM Gateway (лимиты); Backend (сессии диалога) | E14: Redis 7 (docker `redis:7-alpine`); клиент redis-py | F14: Redis 7 в `docker compose`. Лимиты: фиксированная минута, при недоступности хранилища запросы отклоняются (503), а не пропускаются. | G14: Redis выбран против Memcached (нет структур для сессии), таблицы счётчиков в Postgres (по нагрузке справился бы — пик до 0,66 вопроса/с на тираже в максимуме прогноза; счётчик с окном пришлось бы писать вручную) и счётчиков в памяти процесса (лимиты обнуляются при перезапуске, fail-open). | H14: ADR-200, раздел «Сравнение вариантов по слоям», подраздел «Почему PostgreSQL и Redis» | I14: Фиксированное окно даёт двойной лимит на стыке минут — на десятках запросов в минуту это несущественно. | J14: Redis в кластере на постоянном диске. | K14: Redis, StatefulSet + PVC. | L14: Состояние и счётчики должны переживать перезапуск пода. | M14: 2 | N14: 3 | O14: Оценка автора | P14: Без изменений | V14: ADR-200; ADR-400
A15: 13 | B15: Контейнер | C15: Postgres (обращения, слепки, события, телеметрия) | D15: Postgres; Backend (обращения, профили); LLM Gateway (события использования); Сервис работы с обращениями | E15: PostgreSQL 16 (docker `postgres:16-alpine`); драйвер psycopg 3; SQL-скрипты инициализации `docker/postgres/init/` | F15: Postgres 16 в `docker compose`: слепки Биллинга, ЛК и обращений, таблицы обращений, `usage_events`, `quality_reports`. | G15: PostgreSQL выбран против MySQL/MariaDB (нечего добавить к PostgreSQL) и SQLite (один файл, не для нескольких сервисов). Телеметрия остаётся в Postgres, а не в ClickHouse: до ≈0,8 млн событий в год на тираже; замер 2 млн строк — 589 МБ, агрегаты за секунды (ADR-200). | H15: ADR-200, раздел «Сравнение вариантов по слоям», подраздел «Почему PostgreSQL и Redis»; телеметрия — подраздел «Телеметрия: почему Postgres, а не ClickHouse» | I15: На прототипе обращения пишутся прямо в таблицу — микросервиса владельца в закрытой сети нет; слепки вместо живых систем. | J15: Postgres в Kubernetes для состояния, обращений и телеметрии (события использования, отчёты качества); слепки уходят — данные идут через API владельцев. | K15: Postgres, StatefulSet + PVC, резервное копирование. | L15: Целевая схема: своей копии чужих данных быть не должно. Отдельная СУБД под телеметрию не нужна: объём мал (строка «ClickHouse» убрана, её оценка 2–4 чел-дн снята). | M15: 3 | N15: 5 | O15: Оценка автора | P15: Срок хранения подробных событий 12 месяцев, сводная таблица по дням и секции по месяцам; замер на 4 млн строк. | Q15: Postgres: секционирование по месяцам, сводная таблица (материализованное представление или задание по расписанию). | R15: На 12 млн строк агрегат по всей таблице занимает 39 с (замер); без ограничения срока хранения аналитика замедляется. | S15: 2 | T15: 3 | U15: Оценка автора | V15: ADR-100; ADR-200
A16: 14 | B16: Контейнер | C16: Индексация базы знаний (ETL) | D16: ETL индексации; Qdrant; embedding-inference; хранилище документов базы знаний | E16: Python-скрипт `scripts/reindex_kb.py` (сервис `reindex` в docker compose): python-docx → нарезка частей до 300 знаков → Presidio (проверка ПДн) → sentence-transformers (e5-small, CPU) → qdrant-client (blue-green алиас); MVP — K8s CronJob, Celery в коде нет | F16: Сервис `reindex` в compose: одноразовый прогон при подъёме стека (`scripts/reindex_kb.py`), запись в новую коллекцию и атомарное переключение алиаса; Backend только подключается к готовому индексу. Очереди задач и Celery в коде нет. В базе сейчас 27 источников (20 пар FAQ и 7 синтетических документов Word) → 51 фрагмент → 190 векторов. | G16: Планировщик по расписанию выбран против Airflow (платформа ради одного задания) и cron внутри Backend (нет изоляции от ответов абонентам) — по документации, пробного внедрения не было. Celery Beat в коде не используется. Объём MVP — несколько тысяч документов (3 000–5 000), 30 000–100 000 частей (допущение); по замеру на CPU e5-small индексирует их за ≈14–46 мин, BGE-M3 — за ≈2,7–9,6 ч при окне 3 ч; на GPU скорость не измерялась. Отсев дублей при индексации: в коде нет, решение не принято. Варианты (ADR-300, раздел 3): А — MinHash/SimHash + quality_score; Б — центроидное сходство; В — кросс-энкодер офлайн (проект схемы ETL); Г — косинусный порог между частями (предложение автора 25.09.2026). Сравнение — «замер офлайн-роли реранкера», 2–3 чел-дн (ADR-600). | H16: ADR-200, раздел «Сравнение вариантов по слоям», подраздел «Почему индексация — задание по расписанию, а не Airflow» и подраздел «Индексация базы знаний: что реализовано и какой объём»; отсев дублей — ADR-300, раздел 3, подраздел «Офлайн-роль при индексации: отсев дублей (не решено)» | I16: Изоляция GPU между индексацией и онлайн-ответами не решена: массовая переиндексация может увеличить задержку ответа. Свежие документы попадают в индекс с задержкой до ночного окна. | J16: Ночное окно 02:00–05:00: забор документов, очистка, эмбеддинги на GPU, полный реиндекс. Что «окна хватит» на 30–100 тыс. частей на GPU — допущение, скорость на GPU не измерялась; источник и формат настоящих документов владелец не назвал. Отсев дублей: способ не выбран (строка «Реранкер», замер офлайн-роли 2–3 чел-дн), в оценку 4–6 чел-дн отдельно не выделен. | K16: Kubernetes CronJob, окно обслуживания, жёсткая граница по времени. Разбор — python-docx; ПДн — Presidio; эмбеддинги — модель по итогам теста (BGE-M3 предварительно); запись — qdrant-client, blue-green алиас. | L16: Не успели — задание прерывается, продолжение в следующем окне; индекс не повреждается, алиас переключается после полного успеха. | M16: 4 | N16: 6 | O16: Оценка автора | P16: Изоляция GPU между индексацией и онлайн-инференсом. | Q16: Приоритетные очереди либо отдельный GPU-пул. | R16: Появляется вторая постоянная нагрузка на GPU (генерация), и индексация не должна её задерживать. | S16: 3 | T16: 5 | U16: Оценка автора | V16: ADR-400; ADR-600; C4_Deployment
A17: 15 | B17: Контейнер | C17: Агент операций записи (Orchestrator, HITL, аудит) | D17: Agent Orchestrator; Backend; Session State Store (Redis / PostgreSQL); LLM Gateway | E17: Python; собственный конечный автомат (`app/fsm.py`) на перечислениях; сессии в Redis / PostgreSQL | F17: Свой конечный автомат (`app/fsm.py`), покрыт тестами, в продакшене не включён. Регистрация обращений идёт упрощённым путём напрямую в таблицу. | G17: Свой автомат (7 состояний, 10 переходов, 200 строк, перебор всех состояний в тестах) против `transitions` (строковые ключи, дефект уже случался) и LangGraph (второй механизм подтверждения; возможности — ветвление по инструментам, контрольные точки, параллельные ветви — по документации, не пробовались). Вес LangGraph замерен: +34 МиБ ОЗУ и 2,3 с на импорт, ≈2,6% контейнера Backend — не довод против. LangGraph — по триггеру; проверить возможности нечем, пока нет агентного сценария. Другие движки не сравнивались. | H17: ADR-200, раздел «Backend и оркестрация»: строка «Оркестрация агента» и подраздел «Оркестрация агента: собственная таблица переходов, LangGraph — по триггеру» | I17: Оценка function-calling у провайдеров РФ для роли агента — открытый вопрос. Реплика с несколькими задачами разбирается и отвечается по частям; регистрация предлагается по первой подходящей части, несколько черновиков не хранятся; из условий проверяется только наличие долга (ADR-200). Доля реплик с двумя и более задачами по разметке не измерена: выше 5% — переход на LangGraph. | J17: Включение агента: состояние ожидания подтверждения, идемпотентность, аудит (в том числе отказов абонента), проверка черновика до показа. | K17: Свой FSM, Draft Validator, Audit Writer, Session State Store. | L17: Запись данных без подтверждённого сценария дороже по ошибке, чем консультация; ни одна запись без явного подтверждения абонента. | M17: 4 | N17: 6 | O17: Из блока ADR-600: Основная разработка Этапа 2 | P17: Оценка function-calling для роли агента у провайдеров РФ. | Q17: Прогон эталонных сценариев через кандидатов. | R17: От результата зависит, можно ли доверить агенту роль на self-hosted модели. | S17: 5 | T17: 5 | U17: ADR-600 | V17: ADR-100; ADR-200; ADR-400; ADR-600
A18: 16 | B18: Сквозная работа | C18: Переход агента на LangGraph (по триггеру) | D18: Agent Orchestrator; Session State Store (Redis / PostgreSQL); Billing Adapter, Сервис работы с обращениями, Диспетчерская (как инструменты); LLM Gateway | E18: Python; LangGraph `StateGraph`, `interrupt_before` (или без него); хранилище контрольных точек; отключённая телеметрия `langsmith` | F18: Не выполняется: автомат — собственная таблица переходов (`app/fsm.py`, 7 состояний, 10 переходов). Работа появляется только при наступлении одного из четырёх триггеров (модель выбирает следующий шаг после вызова инструмента; шаг ждёт событие дольше 30 минут и должен продолжиться с того же шага; две и более одновременные ветви со своими повторами и слиянием; доля реплик с двумя и более задачами выше 5%). Проверяется при постановке сценария Этапа 2 в разработку, при его изменении и при пересмотре по метрикам Этапа 1; журнал проверки — в ADR-200; пока ни один сценарий не поставлен. | G18: Свой автомат против `transitions` и LangGraph — ADR-200, подраздел «Оркестрация агента». LangGraph нужен, если агент сам выбирает инструмент, если нужны контрольные точки шагов, если появились параллельные ветви со своим состоянием; для фиксированной заявки с одним подтверждением не нужен. | H18: ADR-200, подраздел «Оркестрация агента: собственная таблица переходов, LangGraph — по триггеру», в том числе «В каком случае LangGraph нужен — подробно» | I18: Оценка function-calling у GigaChat и YandexGPT не проведена; возможности LangGraph в проекте не пробовались; телеметрия библиотеки (`langsmith`) не проверена на соответствие 152-ФЗ. Четвёртый триггер — доля реплик абонентов с двумя и более задачами выше 5% (измерение на выгрузке живых обращений и затем ежемесячно по чату). Оценка по триггерам: общая часть 5–9 чел-дн; с триггером 1 — 8–14, 2 — 7–12, 3 — 7–12, 4 — 7–13; все четыре — 14–24 (диапазон 7–24). | J18: Перенос таблицы переходов в граф без изменения состава переходов; `interrupt_before` вместо проверки состояния или не применяется; контрольные точки (Redis с сохранением или Postgres) и удаление ПДн из состояния; при триггере 1 — инструменты (Биллинг, обращения, Диспетчерская) с ограничением шагов, идемпотентностью и аудитом; отключение внешней телеметрии библиотеки; регрессия; при триггере 4 — перенос детектора намерений и очереди задач в граф, условные задачи. | K18: Python; LangGraph `StateGraph`; хранилище контрольных точек — Redis с сохранением или Postgres. | L18: Только по триггеру: возможности, ради которых берут библиотеку, на текущем сценарии проверить нечем. Работа не входит в итог сметы — показана отдельным столбцом. | M18: 7 | N18: 24 | O18: По триггеру (оценка автора) | P18: Без изменений | V18: ADR-200; ADR-600
A19: 17 | B19: Контейнер | C19: Billing Adapter (запись в Биллинг) | D19: Billing Adapter; Биллинг (внешняя система); Agent Orchestrator (HITL Gate) | E19: Python; XML-RPC-клиент к API Биллинга; ключ идемпотентности | F19: Не реализован (запись отложена на Этап 2). Чтение идёт из слепка в Postgres. | G19: Прямой доступ к чужой БД запрещён: только через API владельца. | H19: ADR-400, раздел «Сравнение вариантов по слоям безопасности», подраздел «Как выбран способ доступа к внешним системам» | I19: Сигнатуры API Биллинга от владельца ещё не получены; write-доступ к чужой legacy-системе — отдельная интеграция. | J19: Запись показаний и операций в Биллинг через XML-RPC с ключом идемпотентности. | K19: Отдельный контейнер `Billing Adapter`, XML-RPC API Биллинга. | L19: Единственный разрешённый путь записи в Биллинг; повтор запроса не создаёт дубль. | M19: 4 | N19: 6 | O19: Из блока ADR-600: Основная разработка Этапа 2 | P19: Без изменений | V19: ADR-100; ADR-400
A20: 18 | B20: Контейнер | C20: Сервис работы с обращениями | D20: Сервис работы с обращениями; Микросервис обращений и Диспетчерская (внешние); Agent Orchestrator; Postgres | E20: Python; на прототипе запись в таблицу Postgres, на Этапе 2 — HTTP API владельца (сигнатуры не получены) | F20: Обращение пишется в собственную таблицу Postgres, минуя Orchestrator (`app/inquiries/store.py`). | G20: Целевой путь — внешний микросервис обращений; на прототипе доступа к нему нет. | H20: ADR-400, раздел «Сравнение вариантов по слоям безопасности», подраздел «Как выбран способ доступа к внешним системам»; ADR-100, таблица «Что явно отложено» | I20: Микросервис обращений и его API не готовы принимать реальные запросы; код типов обращений не согласован с владельцем. | J20: Регистрация через API микросервиса обращений; аварийные заявки — в Диспетчерскую (выбор маршрута по типу). | K20: Отдельный контейнер, Route Selector: emergency → Диспетчерская, остальные типы → микросервис. | L20: Обращения должны попадать в систему-владельца, откуда их читают подрядчики и конвейер дообучения. | M20: 3 | N20: 5 | O20: Из блока ADR-600: Основная разработка Этапа 2 | P20: Без изменений | V20: ADR-100; ADR-600
A21: 19 | B21: Контейнер | C21: Document Generator (бланки заявлений) | D21: Document Generator; Backend (выдача бланка); S3 / MinIO (MVP) | E21: Прототип — Python: шаблоны бланков и HTML-лист на печать; MVP — PDF-библиотека (не выбрана) + S3 / MinIO | F21: Готовый бланк отдаётся HTML-листом для печати из каталога (семь образцов по ПП РФ № 644/776). | G21: PDF и S3/MinIO нужны только при путях записи — для консультации избыточны. | H21: ADR-200, раздел «Сравнение вариантов по слоям», подраздел «Документы Этапа 2: PDF и хранилище файлов (решение не принято)» | I21: Настоящие бланки заявлений не согласованы с владельцем — используются образцы. | J21: Рендер PDF из шаблона и слотов, хранение в объектном хранилище, ссылка с ограниченным сроком жизни. | K21: Генерация PDF (библиотека в ADR не выбрана) + S3 / MinIO. | L21: Документ, вложенный в диалог, должен быть файлом, а не страницей печати. | M21: 3 | N21: 4 | O21: Из блока ADR-600: Основная разработка Этапа 2 | P21: Без изменений | V21: ADR-100; ADR-600
A22: 20 | B22: Контейнер | C22: Оркестрация контейнеров | D22: Все контейнеры (Backend, LLM Gateway, Qdrant, Redis, Postgres, ETL, GPU-сервисы) | E22: Прототип — Docker Compose на одной машине; MVP — Kubernetes (nginx Ingress, cert-manager) | F22: `docker compose` на одной машине: postgres, redis, qdrant, reindex, backend. | G22: Compose на одном или нескольких хостах не переживает отказ узла и не обновляется без остановки; Docker Swarm слабее по GPU и заданиям, меньше сообщество; Nomad — реальная альтернатива, если некому эксплуатировать Kubernetes (проще, встроенная интеграция с Vault). Сравнение по документации, ни один вариант кроме Compose не разворачивался (ADR-200, «Почему Kubernetes»). Для одного разработчика и одного хоста Kubernetes избыточен. | H22: ADR-200, раздел «Backend и оркестрация»: строки «Оркестрация контейнеров» и «Оркестрация на прототипе» и подраздел «Почему Kubernetes, а не другая оркестрация» | I22: Решение заказчика проекта (24.09.2026, документально не подтверждено): личный кабинет уже на Kubernetes, размещаемся в том же кластере, эксплуатирует тот же отдел, GPU-узлов нет. Не известны дистрибутив и версия, квоты, классы хранилищ и быстрые диски, как настроено шифрование Kubernetes Secrets и права на них, есть ли своя наблюдаемость, сетевые правила. Управляющая часть кластера в расчёт узлов не заложена — размещена на узлах общего пула (допущение). Накладные расходы кластера — порядка 1 vCPU и 2 ГиБ на узел (допущение): более половины полезной нагрузки на MVP; в общем кластере владельца управляющая часть и системные поды общие, расчёт узлов — верхняя оценка. Nomad с Vault — план Б, менее вероятный. | J22: Размещение в существующем кластере владельца, где работает личный кабинет (эксплуатирует тот же отдел; GPU-узлов нет): пространство имён, квоты, сетевые правила, Ingress, классы хранилищ, манифесты для 16 компонентов, секреты (Kubernetes Secret из GitLab CI variables). Расчёт по допущениям (лист «Sizing», базовый вариант без GPU): 6 узлов на MVP (4 общих и 2 данных), 7 на тираже (+1 GPU-узел под собственную модель); в общем кластере это верхняя оценка заказываемых узлов, стоимость серверов не оценена. | K22: Kubernetes владельца (дистрибутив и версия неизвестны); Ingress и сертификаты — по правилам кластера; манифесты приложения. | L22: Отказоустойчивость, обновление без остановки, пулы узлов с GPU, задания по расписанию. Нагрузка ради этого не нужна: запросы всех подов (11,2 vCPU, 23,6 ГиБ) помещаются на один сервер. | M22: 6 | N22: 9 | O22: Оценка автора | P22: Согласование платформы с владельцем инфраструктуры: решено размещаться в общем кластере с личным кабинетом (эксплуатирует тот же отдел, GPU нет); остаются дистрибутив и версия, квоты, шифрование Secrets и наблюдаемость кластера, отечественное ПО; аргументация записана в ADR-200; при необходимости отдельный ADR. | Q22: — | R22: Для тиража нужна согласованная платформа, включая GPU-пулы; выбор Kubernetes пока предварительный. | S22: 2 | T22: 3 | U22: ADR-600 | V22: ADR-200; ADR-600; C4_Deployment
A23: 21 | B23: Контейнер | C23: Секреты и конфигурация | D23: Backend; LLM Gateway (ключи провайдеров); все контейнеры (конфигурация) | E23: Переменные окружения оболочки (передаются через Compose `${VAR}`); Vault dev-режим (необязательный локальный вариант); MVP — GitLab CI variables, Kubernetes Secret | F23: Переменные окружения оболочки, `.env` приложение не читает; через `docker compose` передаются в контейнер. Vault в dev-режиме — необязательный локальный вариант. | G23: Целевой механизм (решение заказчика проекта, 24.09.2026): GitLab CI variables (masked, protected) + деплой через pipeline → Kubernetes Secret. Сравнение (ADR-200, «Секреты в проде: GitLab CI variables и альтернативы»; по документации, без проверки на стенде владельца): Vault Agent Injector — есть аудит чтения, аренда и замена без пересборки, но нужна новая система (отказоустойчивость, разблокировка, резервные копии) и sidecar в каждом поде; External Secrets Operator или Vault CSI — то же плюс оператор; SOPS или Sealed Secrets — шифрованные секреты в Git, без аудита чтения; Kubernetes Secret вручную — без повторяемости и журнала. Файл `.env` на диске отклонён: секрет в открытом виде лишний, когда есть переменные окружения. | H23: ADR-200, раздел «Секреты и конфигурация» и подраздел «Секреты в проде: GitLab CI variables и альтернативы»; ADR-400 («Что добавляется в контуре MVP») | I23: Нет аудита чтения; значения видны ролям проекта GitLab с правом их читать (по документации Maintainer и выше); шифрование etcd в кластере неизвестно; замена секрета требует деплоя и перезапуска подов; маскирование в логах ограничено по формату значения. Настройки GitLab владельца, права на переменные и версия не проверялись. Прежний выбор Vault Agent Injector отменён как не обоснованный сравнением. | J23: Переменные проекта GitLab CI (masked, protected, по окружениям); job деплоя создаёт Kubernetes Secret без вывода значений в лог; подключение в поды через secretKeyRef или envFrom (изменений кода нет); регламент замены секрета; проверка, что значения не попадают в лог pipeline, образ и манифесты. | K23: GitLab CI/CD variables (masked, protected), pipeline деплоя, Kubernetes Secret; версия и редакция GitLab владельца неизвестны. | L23: Ничего нового не ставится и не эксплуатируется: GitLab уже используется (со слов); приложение читает переменные окружения, как на прототипе. Vault — вариант по условиям пересмотра: аудит чтения, динамические секреты, замена без перезапуска (ADR-400). | M23: 2 | N23: 3 | O23: Оценка автора | P23: Без изменений | V23: ADR-200; ADR-400
A24: 22 | B24: Контейнер | C24: Наблюдаемость (метрики, логи, алерты) | D24: Backend и LLM Gateway (метрики); все контейнеры (логи); Grafana и Zabbix — владельца (не наши контейнеры); отдельные контейнеры Prometheus и Loki — верхняя оценка до ответа владельца (MVP) | E24: prometheus-client (метрики на отдельном порту 9100); MVP — Zabbix и Grafana владельца (Jaeger — по необходимости), дашборды и триггеры как код | F24: Метрики Prometheus на отдельном порту 9100 (в Compose порт не опубликован: с хоста недоступен, внутри контейнера отдаётся), события потока в панели стенда. Дашбордов, сбора логов, трассировки и алертов нет. | G24: Факты со слов заказчика проекта (24.09.2026): в реальном контуре работают Grafana, Zabbix и Jaeger; алерты не настроены. Основной вариант C — Zabbix собирает метрики с порта 9100, Grafana владельца показывает, алерты — триггеры Zabbix; запасной B — свой Prometheus как источник для Grafana (если Zabbix не справится с задержкой P99: квантили по гистограммам штатно не считает — по документации, не проверялось). Prometheus владельца снят (не назван), своя четвёрка и ELK/облако отклонены. Прежнее «Zabbix отклонён: ориентирован на хосты» не проверялось. Сравнение по документации. | H24: ADR-200, раздел «Сравнение вариантов по слоям», подраздел «Наблюдаемость: Grafana владельца и источники данных» | I24: Алерты не настроены: 9 описанных алертов (в том числе «Утечка ПДн в ответе») принимать некому — нет каналов и получателей; предложение автора: настроенный алерт об утечке ПДн — условие включения MVP (согласовать с ИБ). Не известны версии Zabbix, Grafana, Jaeger, подключение Zabbix к Grafana, возможность считать квантили, сбор логов. Трассировки в нашем коде нет (Jaeger в контуре есть). | J24: Дашборды как код (JSON, импорт в Grafana владельца): 5 Golden Signals и 8 метрик ИИ; 9 алертов как триггеры и действия Zabbix; сбор метрик с порта 9100; проверка расчёта P99 в Zabbix до начала работ; определение получателей и каналов оповещения; в логах только отчёт об обезличивании. Проверка на стенде владельца до выбора между Zabbix (C) и своим Prometheus (B): сбор с порта 9100, расчёт P99, доставка алерта, плагин Grafana, нагрузка на Zabbix (1–2 чел-дн, предложение автора). Алерты: триггеры Zabbix (при B — Grafana Alerting; Alertmanager не разворачиваем); алерт об утечке ПДн — сразу, без подавления повторов, получатель от ИБ; алерт о недоступности источника метрик. Трассировка: на MVP без Jaeger — две гистограммы (поиск, вызов провайдера) 0,5–1 чел-дн в пределах оценки; OpenTelemetry → Jaeger — только если P99 разобрать не удаётся, 2–4 чел-дн, оценка автора, в итог не входит. Оценка не пересматривалась (5–8): развёртывание своей связки отпало, добавились интеграция с Zabbix и настройка оповещений. | K24: Zabbix и Grafana владельца; prometheus-client (порт 9100); Jaeger — по необходимости (OpenTelemetry, OTLP); Prometheus и Loki — верхняя оценка до ответа владельца. | L24: Без этого нельзя измерять задержку ответа (P99), долю отказов и утечки ПДн на реальных абонентах; мониторинг и Grafana уже есть у владельца, дублировать их незачем. | M24: 5 | N24: 8 | O24: Оценка автора | P24: Без изменений | V24: C4_Deployment; ADR-200; ADR-500
A25: 23 | B25: Сквозная работа | C25: Алерты и оповещения | D25: Zabbix владельца (триггеры, действия); Backend и LLM Gateway (метрики блокировок и утечек); Grafana владельца (запасной вариант) | E25: Триггеры и действия Zabbix; Grafana Alerting — запасной вариант | F25: 9 алертов описаны (от «Утечка ПДн в ответе» до «ИБ + деградация»), спецификации дашборда в репозитории нет. В реальном контуре алерты не настроены (со слов заказчика проекта, 24.09.2026): каналов оповещения и получателей нет. В нашем коде есть метрики блокировок и утечек, правил и доставки нет. | G25: Триггеры и действия Zabbix (выбраны при основном варианте C) — против Grafana Alerting (при запасном варианте B, если в Zabbix настроить нельзя) и Alertmanager (не разворачиваем: дублирует Zabbix и Grafana владельца). Сравнение по документации, у владельца не проверялось; каналы оповещения не настроены. | H25: ADR-200, подраздел «Наблюдаемость: Grafana владельца и источники данных», блок «Алерты: сравнение вариантов» | I25: Получатели, канал, регламент реакции и эскалация не определены; без них алерты «Утечка ПДн в ответе» и «ИБ + деградация» на MVP не сработают. Версия Zabbix и его возможности по оповещениям неизвестны. Настроены ли алерты в Zabbix вообще или только для нашего сервиса — неизвестно. | J25: 9 алертов как триггеры и действия Zabbix (при запасном варианте B — правила Grafana Alerting); требования к любому варианту: алерт об утечке ПДн приходит сразу и без подавления повторов получателю от ИБ; алерт о недоступности источника метрик; получатели, канал, регламент и эскалация определены до включения MVP (предложение автора, согласовать с ИБ); пороги срабатывания — по замеру на живых данных. | K25: Zabbix владельца (триггеры, действия, каналы); Grafana Alerting — запасной вариант. | L25: Без алерта об утечке ПДн нарушение 152-ФЗ обнаружится не сразу; оценка входит в строку «Наблюдаемость (метрики, логи, алерты)», отдельно не считается. | P25: Без изменений | V25: ADR-200; ADR-400
A26: 24 | B26: Сквозная работа | C26: Трассировка (Jaeger) | D26: Backend; LLM Gateway; клиенты Qdrant, Postgres, Redis; Jaeger владельца | E26: OpenTelemetry (Python), OTLP, Jaeger владельца — по условию | F26: Jaeger в реальном контуре есть (со слов заказчика проекта, 24.09.2026). В нашем коде трассировки нет (библиотек OpenTelemetry и Jaeger в проекте нет). Гистограммы задержки есть для ответа, первого куска, проверки ответа и обезличивания; для поиска в базе знаний и вызова провайдера — нет. | G26: Вариант 1 — без трассировки, метрики по стадиям (по умолчанию для MVP) — против варианта 2 — OpenTelemetry → Jaeger владельца (по условию: P99 по метрикам разобрать не удаётся) и варианта 3 — свой Jaeger (отклонён: в контуре он есть). Сравнение по документации; приём OTLP в Jaeger владельца не проверялся. | H26: ADR-200, подраздел «Наблюдаемость: Grafana владельца и источники данных», блок «Трассировка (Jaeger): сравнение вариантов»; ADR-600, «Трассировка OpenTelemetry → Jaeger — по необходимости» | I26: Без гистограмм поиска и вызова провайдера задержку P99 по стадиям не разобрать. Принимает ли Jaeger владельца OTLP, версия и права — неизвестно. Трассы не должны содержать ПДн в атрибутах спанов. | J26: На MVP без трассировки: две гистограммы (поиск в базе знаний, вызов провайдера) — 0,5–1 чел-дн внутри оценки строки «Наблюдаемость» (оценка автора). Инструментация OpenTelemetry (FastAPI, HTTP-клиенты, клиенты Qdrant, Postgres, Redis) с отправкой по OTLP в Jaeger владельца — только если после гистограмм P99 разобрать не удаётся: 2–4 чел-дн, оценка автора, в итог не входит. | K26: OpenTelemetry (Python), OTLP, Jaeger владельца — по условию. | L26: Трассировка полезна для разбора P99 и TTFT по стадиям, но на четырёх стадиях линейной цепочки метрик обычно хватает; не тратим работу без необходимости. | M26: 2 | N26: 4 | O26: По триггеру (P99 по метрикам разобрать не удаётся; оценка автора) | P26: Без изменений | V26: ADR-200; ADR-600
A27: 25 | B27: Связь | C27: Виджет ↔ Backend | D27: AI-виджет; Backend | E27: HTTP/JSON; поток SSE (`text/event-stream`); контракт OpenAPI 3 | F27: HTTP + поток SSE; контракт описан в OpenAPI (`API_Spec.yaml`), идентификатор абонента — в метаданных запроса. | G27: SSE выбран против WebSocket и периодического опроса: данные идут только от сервера, обычный HTTP проходит через Ingress, формат текстовый. Особенность: EventSource умеет только GET, поэтому виджет читает поток через fetch (POST). | H27: ADR-200, раздел «Сравнение вариантов по слоям», подраздел «Протокол потока ответа: SSE» | I27: Идентификатор абонента передаёт сам клиент — для стенда допустимо, для продакшена нет. | J27: Без изменений | L27: Протокол тот же; токен SSO — в строке про связь с ЛК. | P27: Без изменений | V27: API_Spec.yaml
A28: 26 | B28: Связь | C28: Backend ↔ Платформа ЛК (SSO) | D28: Backend; Платформа ЛК (внешняя) | E28: SSO личного кабинета (протокол не выбран); на прототипе — идентификатор в метаданных запроса | F28: Не подключена: абонент выбирается из справочника стенда. | G28: Сравнение не проводилось: интеграция с ЛК не начата, протокол SSO ещё не известен. | H28: ADR-400, раздел «Сравнение вариантов по слоям безопасности», подраздел «Как выбран способ доступа к внешним системам» (протокол SSO не выбран) | I28: Настоящей SSO-сессии нет; Auth & Session Middleware — целевой компонент. | J28: Профиль и сессия абонента берутся из личного кабинета при открытии диалога. | K28: SSO Платформы ЛК, Auth & Session Middleware в Backend. | L28: Идентификатор абонента должен приходить от доверенной системы, а не от клиента. | M28: 3 | N28: 5 | O28: Из блока ADR-600: Основная разработка Этапа 2 | P28: Без изменений | V28: ADR-400; ADR-600
A29: 27 | B29: Связь | C29: Backend ↔ Биллинг (чтение фактов) | D29: Backend; Биллинг (внешняя) | E29: XML-RPC API Биллинга; на прототипе — слепок в PostgreSQL | F29: Чтение из слепка Биллинга в Postgres; для лицевого счёта: долг, начисления, показания, поверка. | G29: Прямое чтение чужой БД запрещено: только через API владельца. | H29: ADR-400, раздел «Сравнение вариантов по слоям безопасности», подраздел «Как выбран способ доступа к внешним системам» | I29: Сигнатуры API Биллинга от владельца не получены. | J29: Данные абонента запрашиваются у Биллинга в момент вопроса (предрасчёта нет, решение 25.09.2026). | K29: XML-RPC API Биллинга. | L29: Единственный способ доступа к Биллингу; данные нужны онлайн, а не с отставанием предрасчёта. | M29: 1 | N29: 2 | O29: ADR-600 | P29: Без изменений | V29: ADR-400; ADR-600
A30: 28 | B30: Связь | C30: Backend ↔ Диспетчерская | D30: Backend; Сервис работы с обращениями; Диспетчерская (внешняя) | E30: REST API Диспетчерской; на прототипе — локальные данные графика отключений | F30: Данные графика плановых отключений (1939 записей) читаются локально; запись аварийной заявки — заглушка. | G30: Прямой доступ к чужой БД запрещён. | H30: ADR-400, раздел «Сравнение вариантов по слоям безопасности», подраздел «Как выбран способ доступа к внешним системам» | I30: Сигнатуры REST API Диспетчерской от владельца не получены. | J30: Чтение статуса аварийной заявки и зоны по API; запись аварийной заявки после подтверждения абонента. | K30: REST API Диспетчерской. | L30: Единственный разрешённый путь; аварии должны попадать сразу в диспетчерскую. | M30: 1 | N30: 2 | O30: ADR-600 | P30: Без изменений | V30: ADR-100; ADR-400; ADR-600
A31: 29 | B31: Связь | C31: Backend ↔ LLM Gateway | D31: Backend; LLM Gateway | E31: Вызов функции Python в одном процессе; на MVP — HTTP, OpenAI-совместимый протокол | F31: Вызов внутри одного процесса. | G31: Вынос шлюза в отдельный контейнер — следствие целевой схемы развёртывания (C4_Deployment.html); формат конфигурации LiteLLM совместим с прокси, поэтому вынос не требует переписывания. | H31: ADR-200, раздел «LLM-хостинг», подраздел «Как устроен шлюз к модели» | I31: — | J31: Вызов по сети между контейнерами; OpenAI-совместимый протокол. | K31: HTTP внутри кластера. | L31: Следствие выноса шлюза в отдельный контейнер (см. строку LLM Gateway). | P31: Без изменений | V31: ADR-200
A32: 30 | B32: Связь | C32: Backend ↔ Qdrant | D32: Backend; Qdrant | E32: qdrant-client по HTTP (порт 6333) | F32: gRPC (порт 6334) по умолчанию с 24.09.2026, REST (порт 6333) — переключатель QDRANT_PREFER_GRPC=false; запись — отдельным сервисом, Backend только читает готовый индекс. Без TLS и без ключа API. Лимит выдачи: до 300 точек — все точки, выше — top_k × 10. | G32: Клиент по gRPC (с 24.09.2026), а не по REST: замер — gRPC стабильно 6–13 мс, REST через qdrant-client от 6 до 60 мс (топ-20 с payload: 60 мс); прежний довод «HTTP — единицы миллисекунд» не подтвердился. На прототипе (190 точек) REST быстрее (13 против 26 мс). Один хост, Windows; повторить в кластере. | H32: ADR-200, раздел «Сравнение вариантов по слоям», подраздел «Почему Qdrant, а не другая векторная база» (клиент по HTTP, а не gRPC) | I32: Разброс REST не объяснён. Граница точного перебора (300 точек) и PARTS_HEADROOM (10) выбраны по синтетическому замеру (ADR-200, «Значения допущений хранилища»); на реальном корпусе не проверялись. Трафик внутри кластера без TLS и без ключа — решение за ИБ. Замер сделан не на платформе кластера владельца. | J32: gRPC-клиент (сделан на прототипе, 0,5–1 чел-дн, оценка автора); ограниченный лимит выдачи; повторить замер REST и gRPC в кластере владельца, перепроверить PARTS_HEADROOM и границу точного перебора на реальном корпусе, проверить порт 6334 и NetworkPolicy — в пределах теста моделей эмбеддингов. | K32: qdrant-client по gRPC (prefer_grpc, порт 6334). | L32: Стабильные 6–13 мс вместо разброса 6–60 мс; на объёме MVP P99 вдвое ниже (топ-100 с payload: 19,5 против 40,1 мс). | P32: Без изменений | V32: ADR-200; ADR-400; ADR-600
A33: 31 | B33: Связь | C33: LLM Gateway ↔ LLM Provider | D33: LLM Gateway; внешний LLM Provider | E33: HTTPS с проверкой сертификата; LiteLLM (OpenAI-совместимый интерфейс) | F33: HTTPS с проверкой сертификата: YandexGPT (сертификаты доступны). Проверка TLS не отключается никогда. | G33: Отключить проверку сертификата ради GigaChat отклонено — по каналу идут данные абонента; вместо этого переключаемся на другого провайдера. | H33: ADR-400, раздел «Закрыто сейчас» (TLS не отключается); ADR-300, раздел 4 | I33: Для GigaChat нужны корневые сертификаты НУЦ Минцифры — на машине прототипа их нет. | J33: Канал к GigaChat с корневыми сертификатами НУЦ в образе шлюза; автопереключение на резерв. | K33: HTTPS, сертификаты НУЦ Минцифры. | L33: Основной провайдер MVP — GigaChat Pro (входит в работу по строке LLM Provider). | P33: Вызов собственной модели внутри закрытого контура. | Q33: OpenAI-совместимый интерфейс vLLM внутри сети водоканала. | R33: Данные не покидают периметр вообще, а не только территорию РФ. | V33: ADR-400; ADR-300
A34: 32 | B34: Связь | C34: Индексация → Qdrant | D34: ETL индексации; Qdrant | E34: qdrant-client: upsert в новую коллекцию + переключение алиаса (blue-green) | F34: Запись в новую физическую коллекцию и атомарное переключение алиаса (blue-green); удалённые документы уходят при полной пересборке. | G34: Blue-green против обновления на месте: обновление на месте оставляет интервалы с неполным индексом; цена blue-green — двойное хранение на время сборки. | H34: ADR-200, раздел «Сравнение вариантов по слоям», подраздел «Почему Qdrant, а не другая векторная база» (blue-green, а не обновление на месте) | I34: — | J34: Без изменений | L34: Механизм переносится как есть; окно 02:00–05:00 описано в строке про индексацию. | P34: Без изменений | V34: ADR-200
A35: 33 | B35: Сквозная работа | C35: Смета CAPEX/OPEX, NFR, допущения о нагрузке | D35: Все (сквозная работа); GPU-пул и кластер — как предмет сметы | E35: Расчётные таблицы (Capacity_Report.html), формулы sizing | F35: Есть прогнозная модель с минимальным и максимальным сценарием (`Capacity_Report.html`, лист «Прогноз стоимости»): токены на MVP 1 234–101 280 ₽ в месяц, на тираже 3 305 ₽–1,07 млн ₽; цен на серверы и GPU нет. Это не смета: числа не утверждены владельцем (открытый P0). | G35: Не применимо: это работа, а не выбор технологии. | H35: Не применимо: это работа, а не выбор технологии; расчёт — Capacity_Report.html, стоимость — ADR-500 | I35: Разброс стоимости токенов на MVP — ×82 между минимумом и максимумом; без статистики ЛК, колл-центра и живых обращений смета остаётся диапазоном. | J35: Смета по ценам поставщика, расчёт NFR под конкретную GPU-конфигурацию, подтверждение допущений статистикой. Первый пересчёт сметы по данным обращений и ЛК (3–5 чел-дн, после получения данных) и повторный по пилоту (1–2 чел-дн): подставить данные в лист «Прогноз стоимости», пересчитать нагрузку, стоимость и sizing, обновить отчёт о мощности, ADR-500 и матрицу. | K35: — | L35: Без этого нельзя защищать бюджет. | M35: 11.5 | N35: 17 | O35: Из блока ADR-600: P0 | P35: Без изменений | R35: Пересчёт NFR под 90 000 абонентов уже сделан. | V35: ADR-500; ADR-600
A36: 34 | B36: Сквозная работа | C36: Внедрение ответов владельцев данных | D36: Backend (Triage, ответчики); Document Generator; Сервис работы с обращениями | E36: Справочники и тексты в коде и данных; не технология | F36: Пункты, ждущие ответа водоканала: коды типов обращений, текст о качестве воды, четыре процесса вне справочника, настоящие бланки. | G36: Не применимо: это работа, а не выбор технологии. | H36: Не применимо: это работа, а не выбор технологии; перечень пунктов — ADR-600, раздел «Ждут ответа владельцев систем» | I36: Календарный срок определяет владелец, не команда. | J36: Внедрение полученных ответов в справочники и тексты. | K36: — | L36: Разработки не требуют — требуют ответа от водоканала. | M36: 4 | N36: 8 | O36: Из блока ADR-600: Согласования | P36: Без изменений | V36: ADR-600
A37: 35 | B37: Сквозная работа | C37: Документация и согласование ИБ | D37: Все (сквозная работа) | E37: Документы и диаграммы пакета сдачи | F37: Сверка диаграммы Backend с кодом сделана частично; согласования с ИБ по триггерам self-hosted-перехода не было. | G37: Не применимо: это работа, а не выбор технологии. | H37: Не применимо: это работа, а не выбор технологии; состав — ADR-600, раздел «Документация и согласование ИБ» | I37: Календарный срок определяет служба ИБ водоканала. | J37: Полная сверка диаграмм с кодом, нагрузочные и security-сценарии, резюме для CTO. | K37: — | L37: Условие перехода к Этапу 2 — согласование ИБ (ADR-100/600). | M37: 5 | N37: 7.5 | O37: Из блока ADR-600: Документация и ИБ | P37: Согласование перечня триггеров self-hosted-перехода с ИБ. | Q37: — | R37: Триггеры должны быть согласованы до срабатывания, а не после. | V37: ADR-400; ADR-600
A38: 36 | B38: Сквозная работа | C38: GPU-узел в кластере владельца (решение после проверки на реальных данных) | D38: Kubernetes-кластер владельца (новый GPU-узел); embedding-inference; reranker-inference; ETL индексации | E38: Kubernetes: плагин устройств GPU, метки узлов и taints; драйвер видеокарты | F38: В кластере, где работает личный кабинет и где размещается наш контур, GPU-узлов нет (решение заказчика проекта, 24.09.2026). Без них MVP на CPU: эмбеддинги e5-small (36–37 мс на запрос), реранкер выключен, индексация считает эмбеддинги на CPU. | G38: Без GPU: BGE-M3 (300 мс) и реранкер (7,2 с на 20 кандидатах) не укладываются в бюджет 100 мс на CPU. С GPU-узлом: возможны BGE-M3, реранкер, позже собственная модель. Владелец примет решение о GPU-узле только после проверки на реальных данных (24.09.2026): тест моделей идёт на CPU, скорость на GPU — коротким замером на временной видеокарте (ADR-200, «Почему Kubernetes», ADR-600). | H38: ADR-200, подраздел «Почему Kubernetes, а не другая оркестрация» (пункт «GPU»); ADR-300, раздел 2; ADR-600, «GPU-узел в кластере владельца — решение после проверки на реальных данных» | I38: Цена и сроки закупки сервера не оценены; скорость моделей на GPU не измерялась; отдел владельца GPU не эксплуатировал. | J38: Решение — после проверки на реальных данных. Лестница (каждый следующий вариант — только если предыдущий не подошёл): (1) CPU + YandexGPT — базовый: поиск на CPU (e5-small), реранкер выключен, генерация через внешний API (на прототипе YandexGPT; новых потоков данных вовне нет); (2) аренда GPU на месяц — замер скорости, качество на обезличенных текстах, пилот (2–4 чел-дн оценка автора, цена аренды не оценена, нужно согласование с ИБ); (3) покупка — по итогам аренды, решение владельца. Критерии (выбраны заказчиком проекта 24.09.2026): А — hit@3 ≥ 85% и hit@1 ≥ 60% на размеченном наборе живых обращений (рабочие значения, предложение автора, подтверждает владелец после разметки первых 100 обращений); Б — доля ответов, оценённых экспертом как верные и полезные, не ниже 80% на подвыборке не менее 200 (рабочее значение автора); В — пустых выдач из-за реранкера (пуста при «реранкер → порог», но не пуста без реранкера) не более 3% вопросов с ответом в базе (рабочее значение автора, только для реранкера; порядок «порог → реранкер» проходит по построению); D — GPU оправдан при выигрыше над лучшим CPU не менее 5 п.п. по hit@3 или MRR; С — скорость не ниже прототипа: до первого куска ответа медиана ≤ 0,78 с, до конца ответа ≤ 2,6 с (замер прототипа 24.09.2026 на 19 вызовах), поиск P99 ≤ 100 мс. Вариант 1 не подходит при нарушении А, Б или С. Набор для проверки — от 300–400 размеченных обращений (на 30 доверительный интервал ±18 п.п.), сравнение парное. Если решение — покупать (после аренды): закупка сервера и подключение к общему кластеру (драйверы, плагин устройств, метки и запреты размещения, квоты, согласование с отделом) — 3–5 чел-дн без закупки. | K38: Kubernetes: плагин устройств GPU, метки узлов и taints; драйвер видеокарты. | L38: Тест BGE-M3 и реранкеров остаётся в плане при любом исходе: он и даёт основание для решения. Строка отражает работы на случай покупки и в итог сметы не входит. | M38: 3 | N38: 5 | O38: По триггеру (решение владельца после проверки на реальных данных; оценка автора) | P38: Без изменений | V38: ADR-200; ADR-300; ADR-500; ADR-600
A39: 37 | B39: Сквозная работа | C39: Выбор семейства собственной модели и закупка GPU | D39: LLM Provider (собственная модель, тираж); LLM Gateway; GPU-пул | E39: Qwen2.5-32B INT4; vLLM; 1× GPU A100 80 ГБ | F39: Выбор Qwen2.5 сделан по репутации, на эталонном наборе не проверен. | G39: Qwen2.5 (Apache 2.0, сильный русский, 7B→32B без переделки) против Llama 3.x (русский слабее — по репутации; довод «нет варианта под одну карту A100» не подтверждён: 70B в INT4 тоже поместилась бы на 80 ГБ) и открытых весов GigaChat (менее зрелый инструментарий — по общим сведениям, не проверялось). | H39: ADR-300, раздел 4, подраздел «Сравнение семейства self-hosted-модели тиража»; стоимость — ADR-500 | I39: Закупка оборудования — недели или месяцы, это снабжение, не разработка. | J39: Без изменений | P39: Сравнение семейств на эталонном наборе; закупка и ввод GPU-сервера 1× A100 80 ГБ. | Q39: Qwen2.5-32B INT4, vLLM. | R39: Аренда исключена не по цене, а по триггеру (речь о собственной модели генерации; для проверки эмбеддингов и реранкера на MVP аренда на месяц допустима): облачный GPU считается внешним сервисом. | S39: 3 | T39: 5 | U39: ADR-600 | V39: ADR-300; ADR-500; ADR-600
A40: 38 | B40: Сквозная работа | C40: Анализ всех типов обращений на живых данных и повторный выбор моделей | D40: Backend (Triage, ответчики); embedding-inference; reranker-inference; Qdrant (переиндексация при смене модели); LLM Gateway (пороги) | E40: Скрипты замера (`scripts/`), `golden_set/`, PII Filter; результат — Inquiry_Types.xlsx | F40: Замер на 136 настоящих обращениях (по 9 текстов на тип; `Inquiry_Types.xlsx`): слова подбирались на тех же текстах, на отложенной трети охват 75%, точность 65%. Модели выбраны по репутации и замеру задержки. | G40: Не применимо: это работа, а не выбор технологии; сравнение моделей входит в её состав. | H40: ADR-300, разделы 1–2 (решение); ADR-600, раздел «Анализ типов обращений на живых данных» | I40: Метка типа в выгрузке поставлена оператором, знавшим больше, чем написано в тексте; выборка мала; у девяти типов нет запасного k-NN; качество BGE-M3 против e5-small не сравнивалось; пороги k-NN не переносятся на другую модель. | J40: Выгрузка живых обращений (не менее 100 на тип), обезличивание, разметка, анализ всех 16 типов и 6 тем; заново собрать таблицу типов и тем; после этого заново выбрать модели эмбеддингов и запасного классификатора для MVP (сравнение — в строке «Эмбеддинги»). Для каждой реплики размечается число задач и считается доля реплик с двумя и более — триггер 4 перехода агента на LangGraph (выше 5%, ADR-200); в пределах оценки. | K40: Скрипты замера (`scripts/measure_classifier.py`, `measure_search_models.py`), `golden_set/`, PII Filter; результат — обновлённый `Inquiry_Types.xlsx`. | L40: Выбор моделей по репутации нельзя защищать без замера качества на живых данных; смена модели эмбеддингов — самое дорогое решение для отмены (полная переиндексация). Зафиксировано в ADR-300 и ADR-600. Оценка не включает сравнение моделей и расширение классификатора — они учтены в строках «Эмбеддинги» и «Классификатор обращений». | M40: 13 | N40: 19 | O40: Из блока ADR-600: Анализ типов на живых данных | P40: Повторное решение по моделям для тиража по живой статистике MVP. | Q40: Те же скрипты замера; при смене модели — переиндексация и пересчёт порогов k-NN. | R40: Проверить, что модель MVP годится при нагрузке тиража; при необходимости пересчитать пороги и sizing. | S40: 2 | T40: 3 | U40: ADR-600 | V40: ADR-300; ADR-600; Inquiry_Types.xlsx
A41: 39 | B41: Сквозная работа | C41: Несколько задач в одной реплике (доработка после прототипа) | D41: Backend (оркестратор, детектор намерений); LLM Gateway (охранитель, правило в промпте); Session State Store; виджет (кнопки нескольких обращений) | E41: Python; `app/agents/intents.py` (правила на регулярных выражениях); `Orchestrator._stream_parts`; `unperformed_action` в `app/gateway/guardrails.py`; метрика `assistant_multi_intent_total` | F41: На прототипе реализовано: детектор намерений разбирает реплику на задачи правилами (`app/agents/intents.py`), оркестратор отвечает по каждой части, операции без выполнения получают прямой отказ, условие «если долга нет» проверяется по Биллингу; ложное «сделал» блокируется правилом в промпте и в охранителе (`unperformed_action`). Тесты: 22 + 16 + 8. Измерение на выгрузке обращений (`scripts/measure_intents.py`): несколько задач в 1 из 136 текстов (0,7%) — срабатывание детектора, не разметка людьми. | G41: Правила, а не модель: модель на каждой реплике стоила бы времени и токенов, а её разбиение нечем проверить. LangGraph реплику на задачи не разбирает — детектор нужен в любом случае (ADR-200, «Как реализовано: несколько задач в одной реплике»). | H41: ADR-200, подраздел «Как реализовано: несколько задач в одной реплике» (в разделе «Оркестрация агента»); ADR-100, раздел «Несколько задач в одной реплике»; ADR-400 | I41: Предел 300 знаков, перечни глаголов и операций подобраны автором на 136 обращениях регистра, не на репликах чата; точность и полнота на размеченных репликах не измерены. Регистрация только по первой части, из условий проверяется лишь долг, путь `generate` не разбирается, второй бланк перезапишет первый. | J41: Проверка детектора на размеченных репликах чата (точность, полнота, подбор предела и перечней); регистрация нескольких обращений из одной реплики (несколько черновиков, подтверждение каждого, виджет); условия помимо долга; путь `generate`, лимиты и порядок частей. | K41: Python; правила на регулярных выражениях; метрика `assistant_multi_intent_total`; состояние диалога в Redis. | L41: Без этого вторая задача реплики теряется, а модель может написать, что выполнила операцию; доля многозадачных реплик по разметке людьми — условие перехода на LangGraph (триггер 4). | M41: 9 | N41: 14 | O41: Из блока ADR-600: Несколько задач в одной реплике (доработка после прототипа) | P41: Без изменений | V41: ADR-100; ADR-200; ADR-400; ADR-600
A42: 40 | B42: Сквозная работа | C42: Проверка на живых данных: Guardrails и выбор провайдера (YandexGPT, GigaChat) | D42: LLM Gateway; Guardrails; LLM Provider (YandexGPT, GigaChat); Backend; PII Filter | E42: Скрипты замера (`scripts/`), судья качества, метрики Prometheus, LiteLLM Router (цепочки переключения), PII Filter | F42: Проверки Guardrails и выбор провайдеров сделаны без живых вопросов и ответов: на прототипе работает YandexGPT (и локальная модель для тестов), GigaChat недоступен. | G42: Не применимо: это работа, а не выбор технологии; сравнение YandexGPT и GigaChat на живых данных — её содержание. | H42: ADR-300, раздел 4 (провайдеры, «Выбор провайдера для MVP предварительный»); ADR-400, «Проверка работоспособности Guardrails на живых данных»; ADR-600, раздел «Проверка Guardrails и выбор провайдера на живых данных» | I42: Неизвестны частота ложных блокировок и пропусков Guardrails на живых ответах; неизвестно, какой из двух провайдеров лучше на вопросах абонентов и кто из них должен быть запасным. | J42: 1) Проверка работоспособности Guardrails на живых вопросах — не менее 200 из единой выборки 300–400 (общей с тестами эмбеддингов и реранкера; ответы этого прогона без реранкера — базовая линия критерия Б): разметка нарушений, ложные срабатывания и пропуски, правка шаблонов. 2) Тест YandexGPT и GigaChat Pro на той же выборке: качество, время до первого куска и полного ответа, доля блокировок, сбои, стоимость. 3) Решение об основном и запасном провайдере, запись в ADR-300, настройка цепочек переключения. | K42: Скрипты замера (`scripts/run_quality_eval.py`, `scripts/check_yandex.py`), судья качества, метрики Prometheus, LiteLLM Router (цепочки переключения), PII Filter; результат — решение в ADR-300 и конфигурация. | L42: Без живых данных нельзя обосновать ни пороги проверок ответа, ни выбор основного и запасного провайдера. Настройка GigaChat (сертификаты НУЦ, ключ) учтена в строке «LLM Provider» и сюда не входит. Сюда же входит оптимизация синхронной проверки: проверять новый кусок с перекрытием, а не весь накопленный текст, и замер на ответах 500–3 000 знаков (1–2 чел-дн). | M42: 11 | N42: 18 | O42: Из блока ADR-600: Проверка Guardrails и провайдеров на живых данных | P42: Без изменений | V42: ADR-300; ADR-400; ADR-600
C44: Цвет ячеек с оценкой:
D45: цифра прямо из ADR-600
D46: цифра блока ADR-600 (или его доля, распределённая автором) — подтвердить
D47: в ADR-600 нет, оценка автора — подтвердить
D48: изменений на этом этапе нет

Sheet Стоимость
A1: Стоимость доработок по контурам
A2: Единица — человеко-день. 1 неделя = 5 чел-дн; размер команды в ADR-600 не задан, поэтому считается как один исполнитель.
A4: Контур | B4: Итого, чел-дн (мин) | C4: Итого, чел-дн (макс) | D4: Чел-нед (мин) | E4: Чел-нед (макс) | F4: Прямо из ADR-600 (мин) | G4: Прямо из ADR-600 (макс) | H4: Доли блоков ADR-600 (мин) | I4: Доли блоков ADR-600 (макс) | J4: Оценка автора (мин) | K4: Оценка автора (макс) | L4: По триггеру, не в итоге (мин) | M4: По триггеру, не в итоге (макс)
A5: MVP — 8 000 абонентов | B5: =SUM('Матрица'!$M$3:$M$42)-SUMIF('Матрица'!$O$3:$O$42,"По триггеру*",'Матрица'!$M$3:$M$42) | C5: =SUM('Матрица'!$N$3:$N$42)-SUMIF('Матрица'!$O$3:$O$42,"По триггеру*",'Матрица'!$N$3:$N$42) | D5: =B5/5 | E5: =C5/5 | F5: =SUMIF('Матрица'!$O$3:$O$42,"ADR-600",'Матрица'!$M$3:$M$42) | G5: =SUMIF('Матрица'!$O$3:$O$42,"ADR-600",'Матрица'!$N$3:$N$42) | H5: =SUMIF('Матрица'!$O$3:$O$42,"Из блока*",'Матрица'!$M$3:$M$42) | I5: =SUMIF('Матрица'!$O$3:$O$42,"Из блока*",'Матрица'!$N$3:$N$42) | J5: =SUMIF('Матрица'!$O$3:$O$42,"Оценка автора",'Матрица'!$M$3:$M$42) | K5: =SUMIF('Матрица'!$O$3:$O$42,"Оценка автора",'Матрица'!$N$3:$N$42) | L5: =SUMIF('Матрица'!$O$3:$O$42,"По триггеру*",'Матрица'!$M$3:$M$42) | M5: =SUMIF('Матрица'!$O$3:$O$42,"По триггеру*",'Матрица'!$N$3:$N$42)
A6: Тираж — 90 000 абонентов | B6: =SUM('Матрица'!$S$3:$S$42)-SUMIF('Матрица'!$U$3:$U$42,"По триггеру*",'Матрица'!$S$3:$S$42) | C6: =SUM('Матрица'!$T$3:$T$42)-SUMIF('Матрица'!$U$3:$U$42,"По триггеру*",'Матрица'!$T$3:$T$42) | D6: =B6/5 | E6: =C6/5 | F6: =SUMIF('Матрица'!$U$3:$U$42,"ADR-600",'Матрица'!$S$3:$S$42) | G6: =SUMIF('Матрица'!$U$3:$U$42,"ADR-600",'Матрица'!$T$3:$T$42) | H6: =SUMIF('Матрица'!$U$3:$U$42,"Из блока*",'Матрица'!$S$3:$S$42) | I6: =SUMIF('Матрица'!$U$3:$U$42,"Из блока*",'Матрица'!$T$3:$T$42) | J6: =SUMIF('Матрица'!$U$3:$U$42,"Оценка автора",'Матрица'!$S$3:$S$42) | K6: =SUMIF('Матрица'!$U$3:$U$42,"Оценка автора",'Матрица'!$T$3:$T$42) | L6: =SUMIF('Матрица'!$U$3:$U$42,"По триггеру*",'Матрица'!$S$3:$S$42) | M6: =SUMIF('Матрица'!$U$3:$U$42,"По триггеру*",'Матрица'!$T$3:$T$42)
A7: Итого | B7: =SUM(B5:B6) | C7: =SUM(C5:C6) | D7: =SUM(D5:D6) | E7: =SUM(E5:E6) | F7: =SUM(F5:F6) | G7: =SUM(G5:G6) | H7: =SUM(H5:H6) | I7: =SUM(I5:I6) | ... M7: =SUM(M5:M6)
A8: «Оценка автора» — работы, которых нет в ADR-600 (инфраструктура MVP, виджет, вынос шлюза и т. п.); поэтому итог MVP больше, чем «9–13 недель» ADR-600. Столбцы «По триггеру» — работы, которые появятся только при наступлении триггера (переход агента на LangGraph); в итог не входят.
A9: Ставка, ₽ за чел-день (не задана — введите)
A10: Стоимость доработок MVP, ₽ (мин — макс) | D10: =IF($D$9="","",B5*$D$9) | E10: =IF($D$9="","",C5*$D$9)
A11: Стоимость доработок тиража, ₽ (мин — макс) | D11: =IF($D$9="","",B6*$D$9) | E11: =IF($D$9="","",C6*$D$9)
A13: Сверка с блоками ADR-600 (MVP)
A14: Блок ADR-600 | B14: ADR-600 (мин), чел-дн | C14: ADR-600 (макс), чел-дн | D14: Сумма по строкам (мин) | E14: Сумма по строкам (макс) | F14: Сходится? | G14: Как получена цифра ADR-600
A15: P0 | B15: 11.5 | C15: 17 | D15: =SUMIF('Матрица'!$O$3:$O$42,"Из блока ADR-600: P0",'Матрица'!$M$3:$M$42) | E15: =SUMIF('Матрица'!$O$3:$O$42,"Из блока ADR-600: P0",'Матрица'!$N$3:$N$42) | F15: =IF(AND(D15=B15,E15=C15),"да","НЕТ") | G15: ≈2,5–3,5 недели: смета 1–2 дня, NFR 2–3 дня, допущения нагрузки 1 неделя, пересчёт по данным 3–5 + по пилоту 1–2 чел-дн
A16: Согласования | B16: 4 | C16: 8 | D16: =SUMIF('Матрица'!$O$3:$O$42,"Из блока ADR-600: Согласования",'Матрица'!$M$3:$M$42) | E16: =SUMIF('Матрица'!$O$3:$O$42,"Из блока ADR-600: Согласования",'Матрица'!$N$3:$N$42) | F16: =IF(AND(D16=B16,E16=C16),"да","НЕТ") | G16: 1–2 дня на пункт; пунктов принято 4 (коды типов, текст о качестве воды, четыре процесса вне справочника, настоящие бланки) — подтвердить
A17: Качество поиска и классификации | B17: 38 | C17: 56 | D17: =SUMIF('Матрица'!$O$3:$O$42,"Из блока ADR-600: Качество поиска и классификации",'Матрица'!$M$3:$M$42) | E17: =SUMIF('Матрица'!$O$3:$O$42,"Из блока ADR-600: Качество поиска и классификации",'Матрица'!$N$3:$N$42) | F17: =IF(AND(D17=B17,E17=C17),"да","НЕТ") | G17: ≈8–11 недель: классификатор 8–12 + эмбеддинги 10–14 + реранкер 10–15 + судья 6–9 + полнота обезличивания 4–6
A18: Основная разработка Этапа 2 | B18: 20 | C18: 30 | D18: =SUMIF('Матрица'!$O$3:$O$42,"Из блока ADR-600: Основная разработка Этапа 2",'Матрица'!$M$3:$M$42) | E18: =SUMIF('Матрица'!$O$3:$O$42,"Из блока ADR-600: Основная разработка Этапа 2",'Матрица'!$N$3:$N$42) | F18: =IF(AND(D18=B18,E18=C18),"да","НЕТ") | G18: 4–6 недель
A19: Документация и ИБ | B19: 5 | C19: 7.5 | D19: =SUMIF('Матрица'!$O$3:$O$42,"Из блока ADR-600: Документация и ИБ",'Матрица'!$M$3:$M$42) | E19: =SUMIF('Матрица'!$O$3:$O$42,"Из блока ADR-600: Документация и ИБ",'Матрица'!$N$3:$N$42) | F19: =IF(AND(D19=B19,E19=C19),"да","НЕТ") | G19: 1–1,5 недели
A20: Анализ типов на живых данных | B20: 13 | C20: 19 | D20: =SUMIF('Матрица'!$O$3:$O$42,"Из блока ADR-600: Анализ типов на живых данных",'Матрица'!$M$3:$M$42) | E20: =SUMIF('Матрица'!$O$3:$O$42,"Из блока ADR-600: Анализ типов на живых данных",'Матрица'!$N$3:$N$42) | F20: =IF(AND(D20=B20,E20=C20),"да","НЕТ") | G20: 13–19 чел-дн (ADR-600, дополнительно к блоку «Качество поиска и классификации»)
A21: Несколько задач в одной реплике (доработка после прототипа) | B21: 9 | C21: 14 | D21: =SUMIF('Матрица'!$O$3:$O$42,"Из блока ADR-600: Несколько задач в одной реплике (доработка после прототипа)",'Матрица'!$M$3:$M$42) | E21: =SUMIF('Матрица'!$O$3:$O$42,"Из блока ADR-600: Несколько задач в одной реплике (доработка после прототипа)",'Матрица'!$N$3:$N$42) | F21: =IF(AND(D21=B21,E21=C21),"да","НЕТ") | G21: 9–14 чел-дн (ADR-600): проверка детектора на репликах чата 3–4, несколько обращений из одной реплики 3–5, условия помимо долга 2–3, путь generate и лимиты 1–2
A22: Проверка Guardrails и провайдеров на живых данных | B22: 11 | C22: 18 | D22: =SUMIF('Матрица'!$O$3:$O$42,"Из блока ADR-600: Проверка Guardrails и провайдеров на живых данных",'Матрица'!$M$3:$M$42) | E22: =SUMIF('Матрица'!$O$3:$O$42,"Из блока ADR-600: Проверка Guardrails и провайдеров на живых данных",'Матрица'!$N$3:$N$42) | F22: =IF(AND(D22=B22,E22=C22),"да","НЕТ") | G22: 11–18 чел-дн (ADR-600): выборка 1–2, Guardrails 4–6, оптимизация синхронной проверки 1–2, сравнение провайдеров 4–6, решение 1–2
A23: Итого по блокам | B23: =SUM(B15:B22) | C23: =SUM(C15:C22) | D23: =SUM(D15:D22) | E23: =SUM(E15:E22) | F23: =IF(AND(D23=B23,E23=C23),"да","НЕТ") | G23: ADR-600 называет итог ≈22–34 недели (≈110–170 чел-дн); сумма блоков 111,5–169,5 — округление в самом ADR-600
A25: Затраты, которые не выражаются человеко-днями
A26: Контур | B26: Статья | C26: Значение / комментарий | D26: От | E26: До | F26: Единица | G26: Источник
A27: MVP | B27: Токены генерации (YandexGPT Pro, 0,8 ₽ за 1000 токенов) | C27: Минимум — 1 234 ₽/мес (7% абонентов в чате, 30% вопросов до модели, 401 токен на запрос, судья раз в неделю); максимум — 101 280 ₽/мес (35%, 70%, 3 500 токенов, судья каждую ночь). Допущения о спросе данными водоканала не подтверждены; разброс ×82 | D27: 1234 | E27: 101280 | F27: ₽/мес | G27: Capacity_Report; лист «Прогноз стоимости»
A28: Тираж | B28: Токены генерации и судьи качества (тариф YandexGPT Pro 0,8 ₽ за 1000 токенов) | C28: Минимум — 3 305 ₽/мес, максимум — 1,07 млн ₽/мес (0,66 вопроса/с в пике); при собственной модели заменяется CAPEX на карту | D28: 3305 | E28: 1065600 | F28: ₽/мес | G28: Capacity_Report; лист «Прогноз стоимости»
A29: MVP | B29: GPU-сервер под эмбеддинги и реранкер (только если владелец добавит GPU-узел: в кластере GPU нет) | C29: Не оценён отдельной строкой сметы; скорость на GPU не измерялась | F29: ₽ | G29: ADR-500 (открытый пункт)
A30: MVP | B30: Kubernetes-кластер, хранилища, наблюдаемость (железо, размещение, обслуживание) | C30: Не оценены | F30: ₽ | G30: ADR-500 (открытый пункт)
A31: Тираж | B31: Карта A100 80 ГБ (покупка) | C31: OEM ≈927 000 ₽; оригинал/сертифицированная ≈2 368 080 ₽ (аренда 35–50 тыс. ₽/мес исключена триггером). Источник цен в проекте не зафиксирован, коммерческих предложений нет — подтвердить | D31: 927000 | E31: 2368080 | F31: ₽ | G31: ADR-500
A32: Тираж | B32: Сервер-хост, электричество, размещение, обслуживание GPU | C32: Не оценены | F32: ₽ | G32: ADR-500 (открытый пункт)
A34: Все суммы в ₽ — прогнозная модель, не смета: CAPEX/OPEX не утверждены владельцем (ADR-500). Закупка GPU — недели или месяцы лид-тайма, не разработка.

Sheet Источники и допущения
A1: Источники и допущения
A3: • | B3: Единица стоимости | C3: Человеко-день. 1 неделя = 5 чел-дн. Размер команды в ADR-600 не задан — принят один исполнитель.
A4: • | B4: Что сравнивается | C4: Колонки «Сейчас» — то, что работает на прототипе. MVP и тираж — целевые контуры (ADR-100, ADR-200, ADR-500). Строки, где на этапе ничего не меняется, помечены «Без изменений» и серым.
A5: • | B5: Оценки, которые нужно подтвердить | C5: В ADR-600 трудозатраты даны по блокам работ, а не по контейнерам. Доли блоков по строкам распределены автором таблицы так, что сумма по блоку совпадает с оценкой ADR-600 (лист «Стоимость», сверка). Ниже — все ячейки, где цифра не взята прямо из ADR-600.
A6: • | B6: Тираж: расхождение в ADR-600 | C6: Сумма задач перехода к тиражу в ADR-600 — 17–26 чел-дн (3–5 + 5 + 2–3 + 5–10 + 2–3), сам документ округляет до «≈3,5–5 недель». В таблице — построчные значения.
A7: • | B7: Нагрузка и деньги | C7: MVP — 8 000 абонентов; тираж — 90 000. Прогноз токенов и стоимости — минимум и максимум (лист «Прогноз стоимости», `Capacity_Report.html`): учтено, что не все абоненты приходят в чат (7–35%) и только 30–70% вопросов доходит до модели. Цена одна — публичный тариф YandexGPT Pro 0,8 ₽ за 1000 токенов из ADR-500 (не проверялся; тариф GigaChat Pro неизвестен). Цен на серверы и GPU нет. Допущения о спросе данными водоканала не подтверждены; токенов на запрос: измерено 401 (19 вызовов, фрагменты FAQ до 300 знаков), допущение максимума — 3 500. Пересчёт после получения данных — 3–5 чел-дн, по пилоту — 1–2 (блок P0 ADR-600).
A8: • | B8: Замеры 24.09.2026 | C8: Время запроса на CPU: e5-small 22–37 мс, BGE-M3 210–300 мс, реранкер на 20 кандидатах 7,2 с; бюджет поиска 100 мс. Синхронная проверка Guardrails: на ответе ≈800 знаков P95 ≈49 мс, на ≈2 000 знаков P95 ≈120 мс (бюджет 50 мс). YandexGPT, 19 вызовов: время до первого куска — медиана 0,78 с, P90 5,6 с; до конца ответа — медиана 2,6 с. Postgres, 2 млн строк телеметрии: 589 МБ, агрегаты 0,35–1,5 с. Qdrant, 100 000 векторов размерности 1 024: P99 65 мс без фильтра, 37 мс с фильтром. Backend, путь без модели: 117 запросов/с на процесс, 8,5 мс CPU на запрос. Память: обезличиватель 769 МиБ, эмбеддер e5-small +300 МиБ, контейнер Backend 1,32 ГиБ. Redis: ключ квоты ≈0,5 КБ, сессия ≈0,8 КБ на ход. Prometheus: 84 ряда на процесс. Выбранные допущения и расчёт узлов — лист «Sizing».
A9: • | B9: Что не измерялось | C9: Скорость любых моделей на GPU. Качество BGE-M3 и других кандидатов на данных проекта. Выигрыш реранкера над текущим индексом (единственный замер сделан на корпусе из 20 фрагментов). Полнота обезличивания на живых данных. Длина запроса на базе из нескольких тысяч документов. Данные о спросе. Сравнения по документации (pgvector, Milvus, Feature Store, Airflow, Loki, Litestar и др.) замером не проверялись.
A10: • | B10: Внешние зависимости | C10: Сроки внедрения зависят от сигнатур API владельцев (Биллинг, Диспетчерская, микросервис обращений), согласования ИБ, поставки оборудования. Эти ожидания в человеко-днях не учтены.
B12: Ячейки с оценкой автора — подтвердить
A13: № | B13: Контейнер / связь | C13: Контур | D13: Мин | E13: Макс | F13: Основа оценки
A14: ='Матрица'!A3 | B14: ='Матрица'!C3 | C14: MVP | D14: ='Матрица'!M3 | E14: ='Матрица'!N3 | F14: ='Матрица'!O3
A15: ='Матрица'!A4 | B15: ='Матрица'!C4 | C15: MVP | D15: ='Матрица'!M4 | E15: ='Матрица'!N4 | F15: ='Матрица'!O4
A16: ='Матрица'!A5 | B16: ='Матрица'!C5 | C16: MVP | D16: ='Матрица'!M5 | E16: ='Матрица'!N5 | F16: ='Матрица'!O5
A17: ='Матрица'!A6 | B17: ='Матрица'!C6 | C17: MVP | D17: ='Матрица'!M6 | E17: ='Матрица'!N6 | F17: ='Матрица'!O6
A18: ='Матрица'!A7 | B18: ='Матрица'!C7 | C18: MVP | D18: ='Матрица'!M7 | E18: ='Матрица'!N7 | F18: ='Матрица'!O7
A19: ='Матрица'!A8 | B19: ='Матрица'!C8 | C19: MVP | D19: ='Матрица'!M8 | E19: ='Матрица'!N8 | F19: ='Матрица'!O8
A20: ='Матрица'!A9 | B20: ='Матрица'!C9 | C20: MVP | D20: ='Матрица'!M9 | E20: ='Матрица'!N9 | F20: ='Матрица'!O9
A21: ='Матрица'!A10 | B21: ='Матрица'!C10 | C21: MVP | D21: ='Матрица'!M10 | E21: ='Матрица'!N10 | F21: ='Матрица'!O10
A22: ='Матрица'!A11 | B22: ='Матрица'!C11 | C22: MVP | D22: ='Матрица'!M11 | E22: ='Матрица'!N11 | F22: ='Матрица'!O11
A23: ='Матрица'!A12 | B23: ='Матрица'!C12 | C23: MVP | D23: ='Матрица'!M12 | E23: ='Матрица'!N12 | F23: ='Матрица'!O12
A24: ='Матрица'!A13 | B24: ='Матрица'!C13 | C24: MVP | D24: ='Матрица'!M13 | E24: ='Матрица'!N13 | F24: ='Матрица'!O13
A25: ='Матрица'!A14 | B25: ='Матрица'!C14 | C25: MVP | D25: ='Матрица'!M14 | E25: ='Матрица'!N14 | F25: ='Матрица'!O14
A26: ='Матрица'!A15 | B26: ='Матрица'!C15 | C26: MVP | D26: ='Матрица'!M15 | E26: ='Матрица'!N15 | F26: ='Матрица'!O15
A27: ='Матрица'!A15 | B27: ='Матрица'!C15 | C27: Тираж | D27: ='Матрица'!S15 | E27: ='Матрица'!T15 | F27: ='Матрица'!U15
A28: ='Матрица'!A16 | B28: ='Матрица'!C16 | C28: MVP | D28: ='Матрица'!M16 | E28: ='Матрица'!N16 | F28: ='Матрица'!O16
A29: ='Матрица'!A16 | B29: ='Матрица'!C16 | C29: Тираж | D29: ='Матрица'!S16 | E29: ='Матрица'!T16 | F29: ='Матрица'!U16
A30: ='Матрица'!A17 | B30: ='Матрица'!C17 | C30: MVP | D30: ='Матрица'!M17 | E30: ='Матрица'!N17 | F30: ='Матрица'!O17
A31: ='Матрица'!A18 | B31: ='Матрица'!C18 | C31: MVP | D31: ='Матрица'!M18 | E31: ='Матрица'!N18 | F31: ='Матрица'!O18
A32: ='Матрица'!A19 | B32: ='Матрица'!C19 | C32: MVP | D32: ='Матрица'!M19 | E32: ='Матрица'!N19 | F32: ='Матрица'!O19
A33: ='Матрица'!A20 | B33: ='Матрица'!C20 | C33: MVP | D33: ='Матрица'!M20 | E33: ='Матрица'!N20 | F33: ='Матрица'!O20
A34: ='Матрица'!A21 | B34: ='Матрица'!C21 | C34: MVP | D34: ='Матрица'!M21 | E34: ='Матрица'!N21 | F34: ='Матрица'!O21
A35: ='Матрица'!A22 | B35: ='Матрица'!C22 | C35: MVP | D35: ='Матрица'!M22 | E35: ='Матрица'!N22 | F35: ='Матрица'!O22
A36: ='Матрица'!A23 | B36: ='Матрица'!C23 | C36: MVP | D36: ='Матрица'!M23 | E36: ='Матрица'!N23 | F36: ='Матрица'!O23
A37: ='Матрица'!A24 | B37: ='Матрица'!C24 | C37: MVP | D37: ='Матрица'!M24 | E37: ='Матрица'!N24 | F37: ='Матрица'!O24
A38: ='Матрица'!A26 | B38: ='Матрица'!C26 | C38: MVP | D38: ='Матрица'!M26 | E38: ='Матрица'!N26 | F38: ='Матрица'!O26
A39: ='Матрица'!A28 | B39: ='Матрица'!C28 | C39: MVP | D39: ='Матрица'!M28 | E39: ='Матрица'!N28 | F39: ='Матрица'!O28
A40: ='Матрица'!A35 | B40: ='Матрица'!C35 | C40: MVP | D40: ='Матрица'!M35 | E40: ='Матрица'!N35 | F40: ='Матрица'!O35
A41: ='Матрица'!A36 | B41: ='Матрица'!C36 | C41: MVP | D41: ='Матрица'!M36 | E41: ='Матрица'!N36 | F41: ='Матрица'!O36
A42: ='Матрица'!A37 | B42: ='Матрица'!C37 | C42: MVP | D42: ='Матрица'!M37 | E42: ='Матрица'!N37 | F42: ='Матрица'!O37
A43: ='Матрица'!A38 | B43: ='Матрица'!C38 | C43: MVP | D43: ='Матрица'!M38 | E43: ='Матрица'!N38 | F43: ='Матрица'!O38
A44: ='Матрица'!A40 | B44: ='Матрица'!C40 | C44: MVP | D44: ='Матрица'!M40 | E44: ='Матрица'!N40 | F44: ='Матрица'!O40
A45: ='Матрица'!A41 | B45: ='Матрица'!C41 | C45: MVP | D45: ='Матрица'!M41 | E45: ='Матрица'!N41 | F45: ='Матрица'!O41
A46: ='Матрица'!A42 | B46: ='Матрица'!C42 | C46: MVP | D46: ='Матрица'!M42 | E46: ='Матрица'!N42 | F46: ='Матрица'!O42
B48: Документы-источники
B49: ADR-100 | C49: Что сдано и что отложено; таблица «целевой компонент — замена на прототипе»
B50: ADR-200 | C50: Стек по слоям, альтернативы, сравнение Python/Go/Node.js
B51: ADR-300 | C51: Модели: классификация, эмбеддинги, реранкер, генерация, судья
B52: ADR-400 | C52: Безопасность по контурам, открытые пункты
B53: ADR-500 | C53: Ресурсы и стоимость: прототип, MVP, тираж
B54: ADR-600 | C54: План развития и укрупнённые оценки трудозатрат
B55: C4_Deployment, C3/* | C55: Целевая схема развёртывания и компоненты
B56: Код и docker-compose.yml | C56: Проверка колонки «Сейчас»

Sheet Объём по контейнерам
A1: Объём и нагрузка по контейнерам
A2: Нагрузка из модели `Capacity_Report.html` (лист «Прогноз стоимости», допущения спроса данными водоканала не подтверждены): MVP (8 000 абонентов) — 1 680–42 000 вопросов в месяц, пик 0,002–0,058 запроса/с, одновременно 0,007–0,17; тираж (90 000) — 18 900–472 500 вопросов, пик 0,026–0,656 запроса/с, одновременно 0,08–1,97 (минимум–максимум). Сценарии рассчитаны под 10 и 100 тысяч абонентов; в ADR-500 те же контуры — 8 000 и 90 000.
A4: № | B4: Контейнер | C4: Что определяет объём | D4: Что заложено | E4: Статус | F4: Источник
A5: 1 | B5: AI-виджет | C5: Число одновременных пользователей | D5: Отдельного объёма нет: статические файлы, нагрузка — общая (см. Backend). Одновременно до 0,17 запроса на MVP и до 2 на тираже (максимум прогноза). | E5: Расчёт по допущениям | F5: Capacity_Report, раздел 4
A6: 2 | B6: Backend | C6: Число запросов в секунду | D6: Общая нагрузка (см. выше). Замер: путь без модели — 117 запросов/с на один процесс (8,5 мс CPU на запрос), при 4 параллельных запросах медиана 36 мс. Выбрано: 2 реплики на MVP и 3 на тираже по 0,5 и 1 vCPU, ОЗУ 0,5 и 1 ГиБ (лист «Sizing»). | E6: Замер пропускной способности; реплики выбраны | F6: Capacity_Report, раздел 7; ADR-600 (нагрузочные тесты в плане)
A7: 3 | B7: Классификатор обращений (Triage) | C7: Число вопросов; размер набора примеров k-NN | D7: Один проход на вопрос (22–37 мс на CPU, замер). Набор примеров сейчас — 136 обращений; для MVP требуется не менее 100 на тип (около 1 500–2 000 текстов). | E7: Замер задержки; объём набора — план | F7: ADR-300; ADR-600
A8: 4 | B8: LLM Gateway | C8: Число вопросов и лимиты | D8: Общая нагрузка. Лимиты по умолчанию в `app/config.py`: 20 запросов в минуту на абонента, 10 на сессию, 300 на сервис (5 запросов/с); расчётом не обоснованы. Сессия живёт 30 минут. | E8: Настройки прототипа | F8: app/config.py
A9: 5 | B9: PII Filter | C9: Число вопросов и ответов | D9: Один проход на вопрос и один на ответ. Время проверки ответа ≈800 знаков — 30–45 мс (замер), на ≈2 000 знаков — 60–70 мс. Память обезличивателя (Presidio + spaCy) — 769 МиБ (замер). Работает внутри шлюза, отдельного пода нет. | E9: Замер | F9: ADR-400
A10: 6 | B10: Guardrails и судья качества | C10: Число ответов; оценка судьёй | D10: Судья: 1,3–23,7 млн токенов в месяц на MVP и 1,9–174 млн на тираже (эталонный набор из 30 вопросов раз в неделю или каждую ночь плюс 1–5% выборка трафика); допущение: 5 вызовов судьи по ≈2 000 токенов на образец, не измерено. | E10: Расчёт по допущениям | F10: Capacity_Report, лист «Прогноз стоимости»
A11: 7 | B11: LLM Provider | C11: Токены генерации | D11: Токенов на запрос: измерено 401 (19 вызовов, фрагменты FAQ до 300 знаков), допущение максимума — 3 500. Стоимость токенов (генерация и судья) — 1 234–101 280 ₽ в месяц на MVP и 3 305 ₽–1,07 млн ₽ на тираже (минимум–максимум); до модели доходит 30–70% вопросов. Агент Этапа 2 добавит до 44 800 ₽ (MVP) и 504 000 ₽ (тираж) в месяц в максимуме. | E11: Замер (401) и допущение (3 500) | F11: ADR-500; Capacity_Report
A12: 8 | B12: Эмбеддинги (модель поиска) | C12: Вопросы; индексация базы знаний | D12: Один запрос на вопрос; при индексации 30 000–100 000 частей. Скорость на CPU измерена, на GPU — нет. | E12: Замер на CPU; GPU не измерялся | F12: ADR-200; ADR-300
A13: 9 | B13: Реранкер | C13: Вопросы × 20 кандидатов | D13: Одно переранжирование 20 кандидатов на вопрос (до 0,058 вопроса/с на MVP и 0,656 на тираже). На CPU 7,2 с (замер); загрузка GPU не оценивается: скорость на GPU не измерялась. | E13: Замер на CPU; GPU не измерялся | F13: ADR-300; Capacity_Report
A14: 10 | B14: Векторная база (Qdrant) | C14: Размер базы знаний | D14: Несколько тысяч документов (3 000–5 000), 30 000–100 000 векторов размерности 1 024, ≈0,15–0,5 ГБ на диске (замер: 100 000 векторов — 477 МБ, ОЗУ 527 МиБ). От числа абонентов не зависит. Поиск на 100 000 векторов: P99 65 мс без фильтра, 37 мс с фильтром (замер). | E14: Допущение объёма; замер поиска | F14: ADR-200
A15: 11 | B15: Данные абонента (чтение из Биллинга и Диспетчерской) | C15: Число вопросов | D15: Данные не хранятся: читаются из систем в момент вопроса (решение 25 сентября 2026). Верхняя оценка нагрузки на каждую систему — один вызов на вопрос, то есть до 0,058 вызова/с на MVP и 0,656 на тираже в максимуме прогноза (по пути ответа вызовов может быть меньше; доля вопросов, которым нужны данные абонента, не измерена). Скорость и лимиты API владельца неизвестны. Кэш в Redis — только после замера, объём не оценивался. | E15: Допущение; замер API не проводился | F15: ADR-200; ADR-600
A16: 12 | B16: Redis (квоты, состояние диалога) | C16: Одновременные сессии и счётчики | D16: Замер: ключ квоты ≈0,5 КБ, сессия ≈0,8 КБ на ход, срок жизни 30 минут; до 1 200 одновременных сессий ≈4 МБ. Выбрано: 1 экземпляр на MVP, 2 на тираже, 0,25 ГиБ (лист «Sizing»). | E16: Замер; экземпляры выбраны | F16: app/config.py; Capacity_Report
... A22: 18 | B22: Секреты (GitLab CI variables, Kubernetes Secret) | C22: — | D22: Объёма нет. | E22: Не применимо | F22: ADR-400

Sheet Sizing
A1: Расчётный sizing по компонентам (допущения, не результат нагрузочного теста)
A2: Синие ячейки — входные допущения, их можно менять; итоги и число узлов пересчитываются. Основание — в последней колонке.
B3: Расчётная нагрузка | C3: Расчётный пик — 0,1 запроса/с на MVP и 1 запрос/с на тираже; это выше максимума прогноза `Capacity_Report.html` (0,058 и 0,656 запроса/с), одновременно до 0,17 и 1,97 запроса (время ответа 3 с). До модели доходит 70% запросов (максимум прогноза).
B4: CPU на запрос | C4: Путь без модели — 8,5 мс на запрос (замер: один процесс отдаёт 117 запросов/с). Путь с моделью — 0,9 с на ответ в 800 знаков (эмбеддинг 36 мс + обезличивание + проверка ответа на потоке 0,3–0,9 с; на ответе в 2 000 знаков 1,4–4,5 с, замер). При максимуме прогноза (0,46 запроса/с к модели на тираже) это ≈0,41 ядра; на ответах в 2 000 знаков — до 2,1 ядра.
B5: Память | C5: Замер: обезличиватель (Presidio + spaCy `ru_core_news_md`) — 769 МиБ, эмбеддер e5-small — ещё 300 МиБ, контейнер Backend целиком — 1,32 ГиБ. На MVP эмбеддер уходит в отдельный сервис, обезличиватель остаётся в шлюзе.
B6: Данные | C6: Ключ квоты в Redis — 72 байта, с накладными ≈0,5 КБ (замер). Сессия диалога — 1,6 КБ на два хода, ≈0,8 КБ на ход (замер), живёт 30 минут. Диалог — 4 хода ≈ 4 КБ с метаданными (допущение A3 = 4). Срок хранения журнала диалогов принят 90 суток (требование ИБ неизвестно). Строка телеметрии — 308 байт с индексами (замер).
B7: Отказоустойчивость | C7: Минимум 2 реплики у stateless-сервисов; у хранилищ — 1 экземпляр на MVP с ежедневной копией и 2 экземпляра на тираже. Узлов на один больше, чем нужно по запросам (N+1); GPU-узел один, потеря узла = отказ поиска до восстановления.
B8: Секреты | C8: Vault в расчёт не входит: целевой механизм — GitLab CI variables и Kubernetes Secret, отдельных подов нет (ADR-400). Если владелец выберет Vault, понадобится под Vault (допущение: 0,25 vCPU, 0,25 ГиБ, диск 1 ГиБ) и инжектор секретов.
B9: Наблюдаемость | C9: В реальном контуре работают Grafana, Zabbix и Jaeger (решение заказчика проекта, со слов); алерты не настроены. Grafana и Alertmanager в расчёт не входят. Prometheus (запасной источник для задержки P99) и Loki (как собираются логи, неизвестно) оставлены как верхняя оценка до ответа владельца.
B10: GPU в кластере | C10: В кластере владельца, где уже работает личный кабинет, GPU-узлов нет (со слов заказчика проекта). Базовый вариант расчёта — **без GPU**: эмбеддинги `multilingual-e5-small` на CPU (36–37 мс на запрос, замер), реранкер выключен (на CPU 7,2 с), индексация считает эмбеддинги на CPU. Вариант **с GPU** — покупка и подключение узла к кластеру: владелец решит только после проверки на реальных данных (цена не оценена); переключатель на листе «Sizing».
B11: Узлы | C11: Загрузка узла по запросам не выше 70%. Класс узлов: общий — 8 vCPU / 16 ГиБ; данных — 8 vCPU / 32 ГиБ с NVMe; GPU — 8 vCPU / 32 ГиБ и видеокарта 24 ГБ; LLM (тираж) — 16 vCPU / 128 ГиБ и A100 80 ГБ.
B12: GPU-узел в кластере (1 — есть, 0 — нет) | C12: 0
D14: MVP | M14: Тираж
A15: № | B15: Пул | C15: Компонент | D15: Реплик | E15: vCPU на под | F15: ОЗУ, ГиБ на под | G15: Диск, ГиБ на под | H15: Видеопамять, ГиБ на под | I15: vCPU всего | J15: ОЗУ всего, ГиБ | K15: Диск всего, ГиБ | L15: Видеопамять всего, ГиБ | M15: Реплик | N15: vCPU на под | O15: ОЗУ, ГиБ на под | P15: Диск, ГиБ на под | Q15: Видеопамять, ГиБ на под | R15: vCPU всего | S15: ОЗУ всего, ГиБ | T15: Диск всего, ГиБ | U15: Видеопамять всего, ГиБ | V15: Основание
A16: 1 | B16: general | C16: Ingress (nginx) | D16: 2 | E16: 0.25 | F16: 0.25 | G16: 0 | H16: 0 | I16: =D16*E16 | J16: =D16*F16 | K16: =D16*G16 | L16: =D16*H16 | M16: 2 | N16: 0.25 | O16: 0.25 | P16: 0 | Q16: 0 | R16: =M16*N16 | S16: =M16*O16 | T16: =M16*P16 | U16: =M16*Q16 | V16: Допущение. Внешний трафик — единицы запросов в секунду.
A17: 2 | B17: general | C17: AI-виджет (статические файлы) | D17: 2 | E17: 0.1 | F17: 0.1 | G17: 0 | H17: 0 | I17: =D17*E17 | J17: =D17*F17 | K17: =D17*G17 | L17: =D17*H17 | M17: 2 | N17: 0.1 | O17: 0.1 | P17: 0 | Q17: 0 | R17: =M17*N17 | S17: =M17*O17 | T17: =M17*P17 | U17: =M17*Q17 | V17: Допущение. На стенде три статических файла.
A18: 3 | B18: general | C18: Backend (API, классификация, поиск, сборка ответа) | D18: 2 | E18: 0.5 | F18: 0.5 | G18: 0 | H18: 0 | I18: =D18*E18 | J18: =D18*F18 | K18: =D18*G18 | L18: =D18*H18 | M18: 3 | N18: 1 | O18: 1 | P18: 0 | Q18: 0 | R18: =M18*N18 | S18: =M18*O18 | T18: =M18*P18 | U18: =M18*Q18 | V18: Замер: путь без модели — 117 запросов/с на процесс (8,5 мс CPU). 2 реплики нужны для отказоустойчивости, а не для пропускной способности; ОЗУ — допущение (эмбеддер и обезличиватель вынесены).
A19: 4 | B19: general | C19: LLM Gateway (лимиты, обезличивание, проверка ответа) | D19: 2 | E19: 0.5 | F19: 1.5 | G19: 0 | H19: 0 | I19: =D19*E19 | J19: =D19*F19 | K19: =D19*G19 | L19: =D19*H19 | M19: 3 | N19: 1 | O19: 1.5 | P19: 0 | Q19: 0 | R19: =M19*N19 | S19: =M19*O19 | T19: =M19*P19 | U19: =M19*Q19 | V19: Замер ОЗУ: обезличиватель 769 МиБ. CPU: 0,9 с на ответ в 800 знаков — 0,04 ядра на MVP, 0,41 на тираже (максимум прогноза); на ответах в 2 000 знаков до 2,1 ядра (3 реплики × 1 vCPU + предел 2). После оптимизации проверки на потоке запас вырастет.
A20: 5 | B20: general | C20: Billing Adapter, оркестратор записи (Этап 2) | D20: 2 | E20: 0.25 | F20: 0.25 | G20: 0 | H20: 0 | I20: =D20*E20 | J20: =D20*F20 | K20: =D20*G20 | L20: =D20*H20 | M20: 2 | N20: 0.25 | O20: 0.25 | P20: 0 | Q20: 0 | R20: =M20*N20 | S20: =M20*O20 | T20: =M20*P20 | U20: =M20*Q20 | V20: Допущение. До 2 800 диалогов с записью в месяц на MVP и 31 500 на тираже (максимум прогноза, A6 = 40%) — нагрузка ничтожна.
A21: 6 | B21: general | C21: Inquiry Service (маршрутизация обращений, Этап 2) | D21: 2 | E21: 0.25 | F21: 0.5 | G21: 0 | H21: 0 | I21: =D21*E21 | J21: =D21*F21 | K21: =D21*G21 | L21: =D21*H21 | M21: 2 | N21: 0.25 | O21: 0.5 | P21: 0 | Q21: 0 | R21: =M21*N21 | S21: =M21*O21 | T21: =M21*P21 | U21: =M21*Q21 | V21: Допущение автора, не измерялось. Маршрутизация обращений в микросервис обращений и Диспетчерскую; до 2 800 диалогов с записью в месяц на MVP — нагрузка ничтожна.
A22: 7 | B22: general | C22: Document Generator (PDF, Этап 2) | D22: 1 | E22: 0.5 | F22: 1 | G22: 0 | H22: 0 | I22: =D22*E22 | J22: =D22*F22 | K22: =D22*G22 | L22: =D22*H22 | M22: 2 | N22: 0.5 | O22: 1 | P22: 0 | Q22: 0 | R22: =M22*N22 | S22: =M22*O22 | T22: =M22*P22 | U22: =M22*Q22 | V22: Допущение. Библиотека PDF не выбрана; ≈1 бланк на диалог с записью (до 31 500 в месяц на тираже).
A23: 8 | B23: general | C23: ETL индексации (CronJob, окно 02:00–05:00) [вариант с GPU] | D23: =1*$C$12 | E23: 1 | F23: 2 | G23: 5 | H23: 0 | I23: =D23*E23 | J23: =D23*F23 | K23: =D23*G23 | L23: =D23*H23 | M23: =1*$C$12 | N23: 1 | O23: 2 | P23: 5 | Q23: 0 | R23: =M23*N23 | S23: =M23*O23 | T23: =M23*P23 | U23: =M23*Q23 | V23: Допущение. Эмбеддинги считает GPU-сервис; 5 ГиБ — временные файлы документов. Время индексации на GPU не измерялось.
A24: 9 | B24: general | C24: Оценка качества (CronJob, ночной прогон) | D24: 1 | E24: 0.5 | F24: 1 | G24: 0 | H24: 0 | I24: =D24*E24 | J24: =D24*F24 | K24: =D24*G24 | L24: =D24*H24 | M24: 1 | N24: 0.5 | O24: 1 | P24: 0 | Q24: 0 | R24: =M24*N24 | S24: =M24*O24 | T24: =M24*P24 | U24: =M24*Q24 | V24: Допущение. Ходит во внешний API судьи; локальной нагрузки почти нет.
A25: 10 | B25: general | C25: Prometheus | D25: 1 | E25: 0.5 | F25: 1 | G25: 10 | H25: 0 | I25: =D25*E25 | J25: =D25*F25 | K25: =D25*G25 | L25: =D25*H25 | M25: 1 | N25: 0.5 | O25: 1 | P25: 10 | Q25: 0 | R25: =M25*N25 | S25: =M25*O25 | T25: =M25*P25 | U25: =M25*Q25 | V25: Замер: 84 ряда на процесс приложения; допущение: до 20 000 рядов с метриками кластера, хранение 15 суток ≈2,6 ГБ.
A26: 11 | B26: general | C26: Loki | D26: 1 | E26: 0.5 | F26: 1 | G26: 20 | H26: 0 | I26: =D26*E26 | J26: =D26*F26 | K26: =D26*G26 | L26: =D26*H26 | M26: 1 | N26: 0.5 | O26: 1 | P26: 20 | Q26: 0 | R26: =M26*N26 | S26: =M26*O26 | T26: =M26*P26 | U26: =M26*Q26 | V26: Замер: сейчас Backend пишет одну строку (≈65 байт) на вопрос — 2,7 МБ за 30 суток на MVP в максимуме и 31 МБ на тираже. Заложена целевая трассировка до 10 КБ на вопрос (допущение): 0,02–0,42 ГБ на MVP и 0,19–4,7 ГБ на тираже за 30 суток; 20 ГиБ с запасом.
A27: 12 | B27: data | C27: Qdrant | D27: 1 | E27: 1 | F27: 2 | G27: 10 | H27: 0 | I27: =D27*E27 | J27: =D27*F27 | K27: =D27*G27 | L27: =D27*H27 | M27: 2 | N27: 1 | O27: 2 | P27: 10 | Q27: 0 | R27: =M27*N27 | S27: =M27*O27 | T27: =M27*P27 | U27: =M27*Q27 | V27: Расчёт: 30–100 тыс. векторов × 1 024 × 4 байта = 123–410 МБ. Замер: 100 000 векторов — 477 МБ на диске и 527 МиБ ОЗУ (718 МиБ при загрузке); во время blue-green две коллекции и копия — 10 ГиБ. Замер: 100 000 векторов, P99 65 мс. От числа абонентов не зависит; вторая реплика на тираже — для отказоустойчивости.
A28: 13 | B28: data | C28: Postgres (обращения, телеметрия, журнал диалогов) | D28: 1 | E28: 1 | F28: 2 | G28: 20 | H28: 0 | I28: =D28*E28 | J28: =D28*F28 | K28: =D28*G28 | L28: =D28*H28 | M28: 2 | N28: 1 | O28: 2 | P28: 50 | Q28: 0 | R28: =M28*N28 | S28: =M28*O28 | T28: =M28*P28 | U28: =M28*Q28 | V28: Расчёт по максимуму прогноза: журнал диалогов за 90 суток (4 КБ на диалог) — 84 МБ на MVP и 0,95 ГБ на тираже; события использования 0,11 ГБ и 1,2 ГБ в год (308 байт на строку, замер); обращения (заложено 2 КБ на строку, замер по 8 строкам — 0,58 КБ; доля записи 40%) 0,07 и 0,76 ГБ в год. Данные абонента в Postgres не хранятся: они читаются из Биллинга и Диспетчерской в момент вопроса (решение 25 сентября 2026; прежняя строка профиля 24 МБ и 270 МБ снята). Итого до 0,4 ГБ (MVP) и до 4 ГБ (тираж; подробные события хранятся 12 месяцев, старше — сводная таблица); диск с запасом на журнал и копии.
A29: 14 | B29: data | C29: Redis (квоты и сессии) | D29: 1 | E29: 0.1 | F29: 0.25 | G29: 1 | H29: 0 | I29: =D29*E29 | J29: =D29*F29 | K29: =D29*G29 | L29: =D29*H29 | M29: 2 | N29: 0.1 | O29: 0.25 | P29: 1 | Q29: 0 | R29: =M29*N29 | S29: =M29*O29 | T29: =M29*P29 | U29: =M29*Q29 | V29: Замер: ключ квоты ≈0,5 КБ, сессия ≈0,8 КБ на ход, срок жизни 30 минут. До 1 200 одновременных сессий (0,656 запроса/с × 30 мин) × 3 КБ ≈ 4 МБ: объём ничтожен. Отказ Redis отклоняет запросы (fail-closed), поэтому на тираже 2 экземпляра.
A30: 15 | B30: data | C30: MinIO (документы, копии, снимки) | D30: 1 | E30: 0.25 | F30: 0.5 | G30: 100 | H30: 0 | I30: =D30*E30 | J30: =D30*F30 | K30: =D30*G30 | L30: =D30*H30 | M30: 1 | N30: 0.5 | O30: 1 | P30: 400 | Q30: 0 | R30: =M30*N30 | S30: =M30*O30 | T30: =M30*P30 | U30: =M30*Q30 | V30: Расчёт по максимуму прогноза: готовые бланки ≈200 КБ (допущение) × 2 800 в месяц = 6,7 ГБ в год (MVP) и × 31 500 = 76 ГБ в год (тираж), хранение 3 года — 20 и 227 ГБ; копии Postgres за 7 суток до 42 ГБ; документы базы знаний ≈1 ГБ; снимки Qdrant.
A31: 16 | B31: gpu | C31: Эмбеддинги (BGE-M3, inference) [вариант с GPU] | D31: =1*$C$12 | E31: 1 | F31: 4 | G31: 5 | H31: 2 | I31: =D31*E31 | J31: =D31*F31 | K31: =D31*G31 | L31: =D31*H31 | M31: =1*$C$12 | N31: 1 | O31: 4 | P31: 5 | Q31: 2 | R31: =M31*N31 | S31: =M31*O31 | T31: =M31*P31 | U31: =M31*Q31 | V31: Замер: веса 2,14 ГиБ (fp32); на диске 4,25 ГБ — две копии в кэше. Расчёт: в fp16 ≈1,1 ГиБ + запас — ≈2 ГиБ видеопамяти. Скорость на GPU не измерялась.
A32: 17 | B32: gpu | C32: Реранкер (BGE-reranker-v2-m3, inference) [вариант с GPU] | D32: =1*$C$12 | E32: 1 | F32: 3 | G32: 3 | H32: 1.5 | I32: =D32*E32 | J32: =D32*F32 | K32: =D32*G32 | L32: =D32*H32 | M32: =1*$C$12 | N32: 1 | O32: 3 | P32: 3 | Q32: 1.5 | R32: =M32*N32 | S32: =M32*O32 | T32: =M32*P32 | U32: =M32*Q32 | V32: Замер: веса 2,14 ГиБ (fp32). Расчёт: в fp16 ≈1,1 ГиБ + запас — ≈1,5 ГиБ видеопамяти. Скорость на GPU не измерялась; на CPU 7,2 с на 20 кандидатов.
A33: 18 | B33: gpu-llm | C33: Собственная модель (Qwen2.5-32B INT4, vLLM) — по триггеру | D33: 0 | E33: 8 | F33: 64 | G33: 100 | H33: 0 | I33: =D33*E33 | J33: =D33*F33 | K33: =D33*G33 | L33: =D33*H33 | M33: 1 | N33: 8 | O33: 64 | P33: 100 | Q33: 40 | R33: =M33*N33 | S33: =M33*O33 | T33: =M33*P33 | U33: =M33*Q33 | V33: Только на тираже по триггеру. Видеопамять 40 ГБ — допущение (веса INT4 ожидаются 17–20 ГБ, заложено 34 ГБ, плюс кэш); проверка на карте не проводилась.
A34: 19 | B34: general | C34: Эмбеддинги (e5-small на CPU) [вариант без GPU] | D34: =2*(1-$C$12) | E34: 1 | F34: 1.5 | G34: 2 | H34: 0 | I34: =D34*E34 | J34: =D34*F34 | K34: =D34*G34 | L34: =D34*H34 | M34: =2*(1-$C$12) | N34: 1 | O34: 1.5 | P34: 2 | Q34: 0 | R34: =M34*N34 | S34: =M34*O34 | T34: =M34*P34 | U34: =M34*Q34 | V34: Замер: e5-small — 36–37 мс на запрос на CPU и +300 МиБ ОЗУ; BGE-M3 на CPU (300 мс) в бюджет 100 мс не укладывается, реранкер на CPU (7,2 с) не годится и выключен. 2 реплики для отказоустойчивости. Только в варианте без GPU.
A35: 20 | B35: general | C35: ETL индексации: эмбеддинги на CPU (CronJob) [вариант без GPU] | D35: =1*(1-$C$12) | E35: 4 | F35: 4 | G35: 5 | H35: 0 | I35: =D35*E35 | J35: =D35*F35 | K35: =D35*G35 | L35: =D35*H35 | M35: =1*(1-$C$12) | N35: 4 | O35: 4 | P35: 5 | Q35: 0 | R35: =M35*N35 | S35: =M35*O35 | T35: =M35*P35 | U35: =M35*Q35 | V35: Расчёт по замеру: e5-small ≈27 мс на часть (машина с 12 потоками) → 30–100 тыс. частей ≈14–46 мин; на поде с 4 vCPU время не измерялось и может быть в 2–3 раза больше (окно 3 часа). Только в варианте без GPU.
C37: Итог по пулам узлов | P37: Загрузка узла по запросам, не выше | Q37: 0.7
B38: Пул | C38: Класс узла | D38: vCPU узла | E38: ОЗУ узла, ГиБ | F38: Видеопамять узла, ГиБ | G38: Запас на потерю узла (1 — да) | H38: MVP: vCPU | I38: MVP: ОЗУ | J38: MVP: видеопамять | K38: MVP: узлов | L38: Тираж: vCPU | M38: Тираж: ОЗУ | N38: Тираж: видеопамять | O38: Тираж: узлов
B39: general | C39: Общий пул (платформа, приложение, наблюдаемость) | D39: 8 | E39: 16 | F39: 0 | G39: 1 | H39: =SUMIF($B$16:$B$35,$B39,$I$16:$I$35) | I39: =SUMIF($B$16:$B$35,$B39,$J$16:$J$35) | J39: =SUMIF($B$16:$B$35,$B39,$L$16:$L$35) | K39: =IF(H39=0,0,ROUNDUP(MAX(H39/($Q$37*$D39),I39/($Q$37*$E39),IF($F39>0,J39/($Q$37*$F39),0)),0)+$G39) | L39: =SUMIF($B$16:$B$35,$B39,$R$16:$R$35) | M39: =SUMIF($B$16:$B$35,$B39,$S$16:$S$35) | N39: =SUMIF($B$16:$B$35,$B39,$U$16:$U$35) | O39: =IF(L39=0,0,ROUNDUP(MAX(L39/($Q$37*$D39),M39/($Q$37*$E39),IF($F39>0,N39/($Q$37*$F39),0)),0)+$G39)
B40: data | C40: Пул данных (NVMe) | D40: 8 | E40: 32 | F40: 0 | G40: 1 | H40: =SUMIF($B$16:$B$35,$B40,$I$16:$I$35) | I40: =SUMIF($B$16:$B$35,$B40,$J$16:$J$35) | J40: =SUMIF($B$16:$B$35,$B40,$L$16:$L$35) | K40: =IF(H40=0,0,ROUNDUP(MAX(H40/($Q$37*$D40),I40/($Q$37*$E40),IF($F40>0,J40/($Q$37*$F40),0)),0)+$G40) | L40: =SUMIF($B$16:$B$35,$B40,$R$16:$R$35) | M40: =SUMIF($B$16:$B$35,$B40,$S$16:$S$35) | N40: =SUMIF($B$16:$B$35,$B40,$U$16:$U$35) | O40: =IF(L40=0,0,ROUNDUP(MAX(L40/($Q$37*$D40),M40/($Q$37*$E40),IF($F40>0,N40/($Q$37*$F40),0)),0)+$G40)
B41: gpu | C41: GPU-пул (эмбеддинги, реранкер) | D41: 8 | E41: 32 | F41: 24 | G41: 0 | H41: =SUMIF($B$16:$B$35,$B41,$I$16:$I$35) | I41: =SUMIF($B$16:$B$35,$B41,$J$16:$J$35) | J41: =SUMIF($B$16:$B$35,$B41,$L$16:$L$35) | K41: =IF(H41=0,0,ROUNDUP(MAX(H41/($Q$37*$D41),I41/($Q$37*$E41),IF($F41>0,J41/($Q$37*$F41),0)),0)+$G41) | L41: =SUMIF($B$16:$B$35,$B41,$R$16:$R$35) | M41: =SUMIF($B$16:$B$35,$B41,$S$16:$S$35) | N41: =SUMIF($B$16:$B$35,$B41,$U$16:$U$35) | O41: =IF(L41=0,0,ROUNDUP(MAX(L41/($Q$37*$D41),M41/($Q$37*$E41),IF($F41>0,N41/($Q$37*$F41),0)),0)+$G41)
B42: gpu-llm | C42: GPU-пул генерации (тираж) | D42: 16 | E42: 128 | F42: 80 | G42: 0 | H42: =SUMIF($B$16:$B$35,$B42,$I$16:$I$35) | I42: =SUMIF($B$16:$B$35,$B42,$J$16:$J$35) | J42: =SUMIF($B$16:$B$35,$B42,$L$16:$L$35) | K42: =IF(H42=0,0,ROUNDUP(MAX(H42/($Q$37*$D42),I42/($Q$37*$E42),IF($F42>0,J42/($Q$37*$F42),0)),0)+$G42) | L42: =SUMIF($B$16:$B$35,$B42,$R$16:$R$35) | M42: =SUMIF($B$16:$B$35,$B42,$S$16:$S$35) | N42: =SUMIF($B$16:$B$35,$B42,$U$16:$U$35) | O42: =IF(L42=0,0,ROUNDUP(MAX(L42/($Q$37*$D42),M42/($Q$37*$E42),IF($F42>0,N42/($Q$37*$F42),0)),0)+$G42)
B43: Итого узлов | K43: =SUM(K39:K42) | O43: =SUM(O39:O42)
B44: Диск под тома, ГиБ | K44: =SUM($K$16:$K$35) | O44: =SUM($T$16:$T$35)
B46: Не покрыто: скорость моделей на GPU (видеопамять и время индексации — допущения); стоимость серверов и обслуживания; системные поды Kubernetes (≈1 vCPU и 2 ГиБ на узел); управляющая часть Kubernetes размещена на трёх узлах общего пула (допущение); нагрузочный тест не проводился.

Sheet Прогноз стоимости
A1: Прогноз нагрузки и стоимости токенов — минимум и максимум
A2: Синие ячейки — входные допущения: после получения данных по обращениям подставьте новые значения, нагрузка и стоимость пересчитаются. Тариф — публичный тариф YandexGPT Pro из ADR-500, не проверялся; тариф GigaChat Pro неизвестен. Цен на серверы и GPU нет.
A4: № | B4: Входное допущение | C4: Минимум | D4: Максимум | G4: Откуда взято / чем подтвердить
A5: A1 | B5: Доля абонентов, пришедших в чат хотя бы раз в месяц | C5: 0.07 | D5: 0.35 | G5: 70% абонентов обращаются раз в месяц (ADR-500) × доля визитов через чат 10–50%. Не все абоненты пойдут в диалог. Подтвердить: Статистика посещаемости личного кабинета и доля, доходящая до чата
A6: A2 | B6: Диалогов на такого абонента в месяц | C6: 1 | D6: 2.5 | G6: Допущение: 1,0 диалога в месяц (минимум) и 2,5 (максимум), не измерено. Подтвердить: Частота обращений в колл-центр на абонента
A7: A3 | B7: Вопросов внутри одного диалога | C7: 3 | D7: 6 | G7: Минимум — 3 вопроса за визит (ADR-500); максимум 6 — допущение, не измерено. Подтвердить: Анализ живых обращений и пилот
A8: P | B8: Доля вопросов, доходящих до модели | C8: 0.3 | D8: 0.7 | G8: Замер на двух наборах живых текстов: 30% (регистр обращений по телефону и почте) и 70% (форма вопросов Golden Set). Остальные закрывают правила и ответы без модели. Подтвердить: Анализ живых обращений (ADR-600)
A9: T | B9: Токенов на запрос к модели (вход + выход) | C9: 401 | D9: 3500 | G9: Минимум — замер по 19 вызовам YandexGPT (короткие фрагменты FAQ). Максимум — допущение: системный текст + 3 фрагмента по ≈800 токенов. Подтвердить: Пилот на базе из нескольких тысяч документов
A10: A4 | B10: Доля суточных запросов в пиковый час | C10: 0.15 | D10: 0.15 | G10: Допущение: профиль ЖКХ (дни начисления и оплаты). Подтвердить: Статистика ЛК
A11: W | B11: Время ответа, с | C11: 3 | D11: 3 | G11: Целевое значение (DoD). Подтвердить: —
A12: G | B12: Вопросов в эталонном наборе для судьи | C12: 30 | D12: 30 | G12: Замер: `golden_set/quality.json`, 30 вопросов. Подтвердить: —
A13: R | B13: Прогонов эталонного набора в месяц | C13: 4.3 | D13: 30 | G13: Минимум — раз в неделю, максимум — каждую ночь. Подтвердить: Решение команды
A14: C | B14: Вызовов судьи на образец | C14: 5 | D14: 5 | G14: Допущение, не измерено. Подтвердить: Первый прогон с провайдером
A15: J | B15: Токенов на вызов судьи | C15: 2000 | D15: 2000 | G15: Допущение, не измерено. Подтвердить: Первый прогон с провайдером
A16: S_ | B16: Доля ответов, оцениваемых судьёй в проде | C16: 0.01 | D16: 0.05 | G16: Допущение: 1–5% выборка трафика. Подтвердить: Решение команды
... A18: A8 | B18: Токенов на диалог с записью сверх обычных (Этап 2) | C18: 6000 | D18: 20000 | G18: Допущение: 6 000–20 000 токенов, не измерено. Подтвердить: Замер на пилоте
B19: Тариф, ₽ за 1000 токенов | C19: 0.8
B20: Абонентов, MVP | C20: 8000
B21: Абонентов, тираж | C21: 90000
B23: Показатель | C23: MVP, минимум | D23: MVP, максимум | E23: Тираж, минимум | F23: Тираж, максимум
B24: Пришло в чат за месяц, человек | C24: =$C$20*C5 | D24: =$C$20*D5 | E24: =$C$21*C5 | F24: =$C$21*D5
B25: Диалогов в месяц | C25: =C24*C6 | D25: =D24*D6 | E25: =E24*C6 | F25: =F24*D6
B26: Вопросов в месяц | C26: =C25*C7 | D26: =D25*D7 | E26: =E25*C7 | F26: =F25*D7
B27: Запросов к модели в месяц | C27: =C26*C8 | D27: =D26*D8 | E27: =E26*C8 | F27: =F26*D8
B28: Токенов генерации в месяц | C28: =C27*C9 | D28: =D27*D9 | E28: =E27*C9 | F28: =F27*D9
B29: Токенов судьи в месяц (эталонный набор + выборка трафика) | C29: =C12*C13*C14*C15+C27*C16*C14*C15 | D29: =D12*D13*D14*D15+D27*D16*D14*D15 | E29: =C12*C13*C14*C15+E27*C16*C14*C15 | F29: =D12*D13*D14*D15+F27*D16*D14*D15
B30: Генерация, ₽ в месяц | C30: =C28*$C$19/1000 | D30: =D28*$C$19/1000 | E30: =E28*$C$19/1000 | F30: =F28*$C$19/1000
B31: Судья качества, ₽ в месяц | C31: =C29*$C$19/1000 | D31: =D29*$C$19/1000 | E31: =E29*$C$19/1000 | F31: =F29*$C$19/1000
B32: Итого токены, ₽ в месяц | C32: =C30+C31 | D32: =D30+D31 | E32: =E30+E31 | F32: =F30+F31
B33: Итого токены, ₽ в год | C33: =C32*12 | D33: =D32*12 | E33: =E32*12 | F33: =F32*12
B34: Справочно: агент Этапа 2 добавит, ₽ в месяц | C34: =C25*C17*C18*$C$19/1000 | D34: =D25*D17*D18*$C$19/1000 | E34: =E25*C17*C18*$C$19/1000 | F34: =F25*D17*D18*$C$19/1000
B35: Пик, вопросов в секунду | C35: =C26/30*C10/3600 | D35: =D26/30*D10/3600 | E35: =E26/30*C10/3600 | F35: =F26/30*D10/3600
B36: Одновременно обрабатывается | C36: =C35*C11 | D36: =D35*D11 | E36: =E35*C11 | F36: =F35*D11
B38: Расчётная нагрузка sizing: 0,1 запроса/с на MVP и 1 запрос/с на тираже; должна быть не ниже строки «Пик».
