Workbook

Sheet Сводка
A1: Автоматические тесты — сводка
A2: Список собран из самого pytest (сбор тестов без запуска) и docstring-ов; актуален на дату сборки файла.
A4: Уровень | B4: Тестов (функций) | C4: Кейсов | D4: Что проверяет уровень
A5: модульные | B5: =COUNTIF('Тесты'!$B$2:$B$718,A5) | C5: =SUMIF('Тесты'!$B$2:$B$718,A5,'Тесты'!$G$2:$G$718) | D5: Отдельные модули без сети: справочник типов, конечный автомат, поиск, обезличивание, лимиты, ответчики по тарифам и отключениям, сессии, шаблоны бланков.
A6: контрактные | B6: =COUNTIF('Тесты'!$B$2:$B$718,A6) | C6: =SUMIF('Тесты'!$B$2:$B$718,A6,'Тесты'!$G$2:$G$718) | D6: Границы между частями: HTTP-контракт шлюза и спецификация API, порядок работы оркестратора и шлюза, контракт провайдера модели.
A7: Всего | B7: =SUM(B5:B6) | C7: =SUM(C5:C6) | D7: Кейс = один запуск; параметризованный тест даёт несколько кейсов.
A9: Итог обычного прогона (`python -m pytest`) | B9: Кейсов | D9: Комментарий
A10: Проходят | B10: =C7-B11-B12 | D10: Зелёные в обычном прогоне.
A11: Пропускаются (условие не выполнено на этой машине) | B11: 3 | D11: Три теста в test_metrics.py сверяют метрики со спецификацией дашборда; файла спецификации в пакете сдачи нет, поэтому они пропускаются.
A12: Выключены маркером `live` (нужна запущенная Ollama) | B12: 10 | D12: Запуск явно: `python -m pytest -m live`.
A13: Всего собрано | B13: =C7
A15: Как запустить
A16: python -m pytest — весь обычный прогон
A17: python -m pytest tests/unit — только модульные
A18: python -m pytest tests/contract — только контрактные
A19: python -m pytest -m live — живые тесты (нужна Ollama)

Sheet Тесты
A1: № | B1: Уровень | C1: Файл | D1: Класс | E1: Тест | F1: Что проверяет | G1: Кейсов | H1: Пометки
A2: 1 | B2: контрактные | C2: contract/test_api.py | E2: test_только_два_адреса_плюс_стенд | F2: Контракт — два адреса: /models удалён из контракта, лишнего быть не должно. | G2: 1
A3: 2 | B3: контрактные | C3: contract/test_api.py | E3: test_проверка_доступности_отвечает_без_авторизации | F3: Контракт: security: [] — заголовков не требуется. | G3: 1
A4: 3 | B4: контрактные | C4: contract/test_api.py | E4: test_ответ_приходит_потоком | F4: Ответ приходит потоком | G4: 1
A5: 4 | B5: контрактные | C5: contract/test_api.py | E5: test_события_потока_разделены_пустой_строкой | F5: Требование формата: иначе потребитель склеит два события в одно. | G5: 1
A6: 5 | B6: контрактные | C6: contract/test_api.py | E6: test_русский_текст_в_потоке_не_экранируется | F6: Иначе стенд показал бы абоненту последовательности вида \u043f. | G6: 1
A7: 6 | B7: контрактные | C7: contract/test_api.py | E7: test_ответ_целиком_приходит_обычным_json | F7: Ответ целиком приходит обычным json | G7: 1
A8: 7 | B8: контрактные | C8: contract/test_api.py | E8: test_неверный_запрос_даёт_400_в_формате_rfc7807 | F8: Неверный запрос даёт 400 в формате rfc7807 | G8: 1
A9: 8 | B9: контрактные | C9: contract/test_api.py | E9: test_слишком_длинный_запрос_отклоняется | F9: Ограничение длины запроса — 2000 символов. | G9: 1
A10: 9 | B10: контрактные | C10: contract/test_api.py | E10: test_у_отказов_есть_время_повтора | F10: RFC 7807 требует его для 429; ADR-400 — для 503. | G10: 2
A11: 10 | B11: контрактные | C11: contract/test_api.py | E11: test_ошибка_в_потоке_приходит_событием_с_тем_же_телом | F11: Решение 4 в моделях: один формат ошибки на оба пути. | G11: 1
A12: 11 | B12: контрактные | C12: contract/test_api.py | E12: test_идентификаторы_доходят_до_шлюза | F12: Без них не считаются лимиты и не пишется аудит. | G12: 1
A13: 12 | B13: контрактные | C13: contract/test_api.py | E13: test_стенд_отдаётся_по_корневому_адресу | F13: Только на прототипе: в рабочем контуре виджет живёт в кабинете абонента. | G13: 1
... A66: 65 | B66: контрактные | C66: contract/test_llm_gateway.py | E66: test_у_ошибки_есть_опознаватель_запроса | F66: Без него жалобу абонента невозможно связать с записью в журнале. | G66: 1
A67: 66 | B67: контрактные | C67: contract/test_llm_gateway.py | E67: test_живой_вызов_яндекса | F67: Сквозная проверка на реальном провайдере. Запускать: pytest -m live. | G67: 1 | H67: живой тест (нужна Ollama, в обычном прогоне выключен)
A68: 67 | B68: контрактные | C68: contract/test_llm_gateway.py | E68: test_внутренний_текст_ошибки_не_доходит_до_абонента | F68: Найдено живой проверкой: абоненту показывался адрес, порт и адрес объекта в памяти. И непонятно, и раскрывает устройство системы. | G68: 2
A69: 68 | B69: контрактные | C69: contract/test_llm_gateway.py | E69: test_внутренний_текст_не_доходит_и_в_потоке | F69: Тот же путь, второй режим: ошибка внутри уже начатого потока. | G69: 1
A70: 69 | B70: контрактные | C70: contract/test_llm_gateway.py | E70: test_прогрев_поднимает_тяжёлые_зависимости | F70: Найдено живой проверкой: восемь секунд до первого куска ответа. | G70: 1
A71: 70 | B71: контрактные | C71: contract/test_llm_gateway.py | E71: test_интерфейс_прогревает_шлюз_при_запуске | F71: Прогрев бесполезен, если его никто не вызывает. | G71: 1
A72: 71 | B72: контрактные | C72: contract/test_llm_gateway.py | E72: test_ответ_по_синтетике_помечен_оговоркой | F72: Ответ по выдуманной процедуре обязан быть отличим от ответа по настоящему регламенту — иначе на демонстрации его примут за второе. | G72: 1
A73: 72 | B73: контрактные | C73: contract/test_llm_gateway.py | E73: test_ответ_по_настоящему_источнику_оговорки_не_несёт | F73: Иначе оговорка обесценится: она стоит на каждом ответе и её перестают читать. | G73: 1
A74: 73 | B74: контрактные | C74: contract/test_llm_gateway.py | E74: test_хватает_одного_синтетического_фрагмента | F74: Смесь настоящего и выдуманного — самый опасный случай: ответ выглядит обоснованным, а часть его построена на составленной нами процедуре. | G74: 1
A75: 74 | B75: контрактные | C75: contract/test_llm_gateway.py | E75: test_расход_из_последнего_куска_доходит_до_события_завершения | F75: Кусок с расходом не несёт текста, и его легко потерять. | G75: 1
A76: 75 | B76: контрактные | C76: contract/test_llm_gateway.py | E76: test_потоковый_путь_запрашивает_расход_у_провайдера | F76: Без stream_options провайдер расход не присылает вовсе — проверено на обоих. Параметр обязан уходить именно в потоковом вызове. | G76: 1
A77: 76 | B77: контрактные | C77: contract/test_llm_gateway.py | E77: test_молчание_провайдера_о_расходе_не_ломает_поток | F77: Провайдер может не прислать расход — тогда ноль, но ответ доходит. | G77: 1
A78: 77 | B78: контрактные | C78: contract/test_llm_gateway.py | E78: test_поток_пишет_событие_использования | F78: Поток пишет событие использования | G78: 1
A79: 78 | B79: контрактные | C79: contract/test_llm_gateway.py | E79: test_ответ_целиком_пишет_событие_использования | F79: Ответ целиком пишет событие использования | G79: 1
... A86: 85 | B86: контрактные | C86: contract/test_llm_gateway.py | E86: test_ответ_вне_выборки_судье_не_отдаётся | F86: Ответ вне выборки судье не отдаётся | G86: 1
A87: 86 | B87: контрактные | C87: contract/test_local_model_live.py | E87: test_модель_поднята_и_загружена | F87: Преполёт на живой Ollama: сервис отвечает, нужная модель на месте. | G87: 1 | H87: живой тест (нужна Ollama, в обычном прогоне выключен)
A88: 87 | B88: контрактные | C88: contract/test_local_model_live.py | E88: test_модель_отвечает_по_русски | F88: Модель отвечает по русски | G88: 1 | H88: живой тест (нужна Ollama, в обычном прогоне выключен)
A89: 88 | B89: контрактные | C89: contract/test_local_model_live.py | E89: test_ответ_приходит_потоком_а_не_одним_куском | F89: Правило потоковой выдачи: локальный backend обязан уметь поток так же, как внешний. | G89: 1 | H89: живой тест (нужна Ollama, в обычном прогоне выключен)
A90: 89 | B90: контрактные | C90: contract/test_orchestrator.py | E90: test_прямой_ответ_не_вызывает_провайдера | F90: Требование ADR-100: ответ не стоит ни токенов, ни ожидания. | G90: 1
A91: 90 | B91: контрактные | C91: contract/test_orchestrator.py | E91: test_оговорка_доходит_обоими_путями | F91: Отметка актуальности бесполезна, если теряется в одном из режимов. | G91: 1
A92: 91 | B92: контрактные | C92: contract/test_orchestrator.py | E92: test_путь_ответа_виден_в_маршрутизации | F92: Иначе прямой ответ неотличим от сгенерированного при разборе жалобы. | G92: 1
A93: 92 | B93: контрактные | C93: contract/test_orchestrator.py | E93: test_молчание_ответчика_уводит_на_обычный_путь | F93: «Не мой случай» не должно превращаться в отказ. | G93: 1
A94: 93 | B94: контрактные | C94: contract/test_orchestrator.py | E94: test_ответчики_опрашиваются_по_порядку | F94: Первый, кто взялся, и отвечает: иначе порядок стал бы случайным, а с ним и ответ на вопрос, попадающий сразу в две темы. | G94: 1
A95: 94 | B95: контрактные | C95: contract/test_orchestrator.py | E95: test_лимиты_проверяются_и_на_прямом_пути | F95: Запрос, отвечаемый без модели, до шлюза не доходит. | G95: 1
A96: 95 | B96: контрактные | C96: contract/test_orchestrator.py | E96: test_отказ_хранилища_на_прямом_пути_даёт_503 | F96: ADR-400: недоступность хранилища — это 503, а не 429. | G96: 1
A97: 96 | B97: контрактные | C97: contract/test_orchestrator.py | E97: test_контекст_ищется_и_доходит_до_шлюза | F97: Backend ищет, шлюз получает промпт с уже собранным контекстом. | G97: 1
A98: 97 | B98: контрактные | C98: contract/test_orchestrator.py | E98: test_переданный_контекст_не_перетирается | F98: Служебные вызовы передают контекст сами. | G98: 1
A99: 98 | B99: контрактные | C99: contract/test_orchestrator.py | E99: test_без_базы_знаний_запрос_идёт_как_есть | F99: Отсутствие поиска — не отказ: модель отвечает без опоры на регламенты. | G99: 1
A100: 99 | B100: контрактные | C100: contract/test_orchestrator.py | E100: test_прямой_путь_не_ищет_контекст | F100: Отключения и регламентные ответы модели не отдают — искать им нечего. | G100: 1
A101: 100 | B101: контрактные | C101: contract/test_orchestrator.py | E101: test_шлюз_не_знает_про_прямые_ответы | F101: Ответчик жил в шлюзе, пока не было оркестратора, и слой был не тот. | G101: 1
... A290: 289 | B290: модульные | C290: unit/test_generate_charges.py | E290: test_свежие_периоды_не_оплачены_раньше_старых | F290: Абонент, заплативший за август, но не за июнь, — признак того, что долг разносится не с того конца. | G290: 1
A291: 290 | B291: модульные | C291: unit/test_generate_charges.py | E291: test_одно_зерно_даёт_тот_же_файл | F291: Требование проекта: повторный запуск с тем же зерном даёт побайтово тот же файл. Случайность нужна для правдоподобия, а не для сюрпризов. | G291: 1 | H291: медленный (грузит языковую модель)
A292: 291 | B292: модульные | C292: unit/test_generate_kb_docs.py | E292: test_документы_собираются | F292: Документы собираются | G292: 1
A293: 292 | B293: модульные | C293: unit/test_generate_kb_docs.py | E293: test_в_каждом_документе_пометка_первым_абзацем | F293: До содержания, а не после: читающий не должен добраться до текста, не увидев, что документ синтетический. | G293: 1
A294: 293 | B294: модульные | C294: unit/test_generate_kb_docs.py | E294: test_пометка_в_колонтитуле_и_свойствах | F294: Первый абзац уходит за кадр на скриншоте и при печати со второй страницы. | G294: 1
A295: 294 | B295: модульные | C295: unit/test_generate_kb_docs.py | E295: test_у_документов_есть_структура_ради_которой_они_и_нужны | F295: Смысл этих файлов — проверить, уважает ли нарезка границы разделов. | G295: 1
A296: 295 | B296: модульные | C296: unit/test_generate_kb_docs.py | E296: test_вложенные_уровни_есть_хотя_бы_в_одном_документе | F296: Ровные разделы одного уровня нарезку не проверяют. | G296: 1
A297: 296 | B297: модульные | C297: unit/test_generate_kb_docs.py | E297: test_нормативные_ссылки_только_наблюдавшиеся | F297: Выдуманная ссылка на пункт постановления — тот же класс ошибки, что недостоверные цифры в чужих черновиках. | G297: 1
A298: 297 | B298: модульные | C298: unit/test_generate_kb_docs.py | E298: test_типы_обращений_взяты_из_справочника_владельца | F298: Не наш перечень: коды синтетические, но названия пришли от владельца. | G298: 1
A299: 298 | B299: модульные | C299: unit/test_golden_set.py | E299: test_набор_нужного_размера | F299: Цель — 50–100 вопросов. | G299: 1
A300: 299 | B300: модульные | C300: unit/test_golden_set.py | E300: test_опознаватели_не_повторяются | F300: Опознаватели не повторяются | G300: 1
A301: 300 | B301: модульные | C301: unit/test_golden_set.py | E301: test_подмножества_известны | F301: Подмножества известны | G301: 1
A302: 301 | B302: модульные | C302: unit/test_golden_set.py | E302: test_ожидаемые_фрагменты_существуют | F302: Опечатка в идентификаторе фрагмента дала бы вечный промах, неотличимый от настоящего промаха поиска. | G302: 1
A303: 302 | B303: модульные | C303: unit/test_golden_set.py | E303: test_ожидание_соответствует_подмножеству | F303: real и corpus обязаны чего-то ждать, остальные — ничего. | G303: 1
... A306: 305 | B306: модульные | C306: unit/test_golden_set.py | E306: test_каждую_пару_faq_кто_то_ждёт | F306: Иначе часть корпуса не проверяется вовсе, и её поломка пройдёт незаметно. | G306: 1
A307: 306 | B307: модульные | C307: unit/test_golden_set.py | E307: test_каждая_ссылка_на_обращение_разрешается | F307: Сдвиг строк в выгрузке молча переразметил бы весь набор. | G307: 1 | H307: условный пропуск
A308: 307 | B308: модульные | C308: unit/test_guardrails.py | E308: test_сценарий_1_попытка_выведать_системный_промпт | F308: Guardrails блокирует ответ; системный промпт не раскрывается. | G308: 1
A309: 308 | B309: модульные | C309: unit/test_guardrails.py | E309: test_сценарий_2_чужие_персональные_данные_в_ответе | F309: Проверка обрывает поток; ответ чужих данных не содержит. | G309: 1
A310: 309 | B310: модульные | C310: unit/test_guardrails.py | E310: test_сценарий_3_данные_на_входе_обезличиваются | F310: Третий сценарий закрывается фильтром входа, а не охранителями. | G310: 1
A311: 310 | B311: модульные | C311: unit/test_guardrails.py | E311: test_сценарий_4_провокация_недопустимого_тона | F311: Вместо сгенерированного ответа уходит безопасная заглушка. | G311: 1
A312: 311 | B312: модульные | C312: unit/test_guardrails.py | E312: test_нормальный_ответ_проходит | F312: Нормальный ответ проходит | G312: 1
A313: 312 | B313: модульные | C313: unit/test_guardrails.py | E313: test_пустой_ответ_не_ломает_проверку | F313: Пустой ответ не ломает проверку | G313: 1
A314: 313 | B314: модульные | C314: unit/test_guardrails.py | E314: test_утечка_отличима_от_прочих_блокировок | F314: Дашборд: утечка вынесена в отдельный виджет, а не смешана с общим счётчиком. | G314: 1
A315: 314 | B315: модульные | C315: unit/test_guardrails.py | E315: test_значения_данных_не_попадают_в_вердикт | F315: Вердикт уходит в метрики и журнал — значений в нём быть не должно. | G315: 1
A316: 315 | B316: модульные | C316: unit/test_guardrails.py | E316: test_блокировка_помечается_особой_причиной_завершения | F316: Иначе в аналитике обрыв выглядел бы как нормально законченный ответ. | G316: 1
A317: 316 | B317: модульные | C317: unit/test_guardrails.py | E317: test_заглушка_не_подсказывает_причину | F317: Сообщение «заблокировано из-за данных» само выдавало бы, что удалось вытянуть. | G317: 1
A318: 317 | B318: модульные | C318: unit/test_guardrails.py | E318: test_чистый_поток_доходит_целиком | F318: Чистый поток доходит целиком | G318: 1
A319: 318 | B319: модульные | C319: unit/test_guardrails.py | E319: test_поток_обрывается_на_нарушении | F319: Правило потоковой выдачи требует потока, но не ценой показа запрещённого. | G319: 1
... A338: 337 | B338: модульные | C338: unit/test_inquiry_store.py | E338: test_схема_лежит_одним_файлом_и_он_на_месте | F338: Postgres применяет её при создании тома, хранилище — на живой базе. | G338: 1
A339: 338 | B339: модульные | C339: unit/test_inquiry_store.py | E339: test_живой_postgres_держит_уникальность_ключа | F339: Проверяет то, чего дубль проверить не может. | G339: 1 | H339: живой тест (нужна Ollama, в обычном прогоне выключен)
A340: 339 | B340: модульные | C340: unit/test_inquiry_type_fallback.py | E340: test_ближайший_пример_даёт_тип | F340: Ближайший пример даёт тип | G340: 1
A341: 340 | B341: модульные | C341: unit/test_inquiry_type_fallback.py | E341: test_ниже_порога_это_none | F341: Ниже порога это none | G341: 1
A342: 341 | B342: модульные | C342: unit/test_inquiry_type_fallback.py | E342: test_маленький_разрыв_до_другого_типа_это_none | F342: Маленький разрыв до другого типа это none | G342: 1
A343: 342 | B343: модульные | C343: unit/test_inquiry_type_fallback.py | E343: test_разрыв_считается_только_до_другого_типа | F343: Разрыв считается только до другого типа | G343: 1
A344: 343 | B344: модульные | C344: unit/test_inquiry_type_fallback.py | E344: test_пустой_запрос_это_none | F344: Пустой запрос это none | G344: 1
A345: 344 | B345: модульные | C345: unit/test_inquiry_type_fallback.py | E345: test_без_примеров_это_none | F345: Без примеров это none | G345: 1
A346: 345 | B346: модульные | C346: unit/test_inquiry_type_fallback.py | E346: test_отказ_эмбеддера_не_пробрасывается | F346: Отказ эмбеддера не пробрасывается | G346: 1
A347: 346 | B347: модульные | C347: unit/test_inquiry_type_fallback.py | E347: test_примеры_проэмбечены_один_раз | F347: Примеры проэмбечены один раз | G347: 1
A348: 347 | B348: модульные | C348: unit/test_inquiry_type_fallback.py | E348: test_примеры_ограничены_семью_регистрируемыми_типами | F348: Примеры ограничены семью регистрируемыми типами | G348: 1
A349: 348 | B349: модульные | C349: unit/test_inquiry_type_fallback.py | E349: test_реальные_формулировки_живой_эмбеддер | F349: Реальные формулировки живой эмбеддер | G349: 1 | H349: живой тест (нужна Ollama, в обычном прогоне выключен)
A350: 349 | B350: модульные | C350: unit/test_intents.py | E350: test_две_задачи_делятся | F350: Две задачи делятся | G350: 5
A351: 350 | B351: модульные | C351: unit/test_intents.py | E351: test_одна_задача_не_режется | F351: Перерез вреднее недореза: два ответа на один вопрос сбивают абонента. | G351: 6
A352: 351 | B352: модульные | C352: unit/test_intents.py | E352: test_вопрос_как_передать_показания_не_операция | F352: «Как передать» — вопрос о порядке, на него отвечает база знаний, а не отказ. | G352: 1
A353: 352 | B353: модульные | C353: unit/test_intents.py | E353: test_просьба_выполнить_операцию_узнаётся | F353: Просьба выполнить операцию узнаётся | G353: 4
A354: 353 | B354: модульные | C354: unit/test_intents.py | E354: test_условная_часть_привязана_к_долгу | F354: Условная часть привязана к долгу | G354: 1
A355: 354 | B355: модульные | C355: unit/test_intents.py | E355: test_условие_про_долг_названное_прямо | F355: Условие про долг названное прямо | G355: 1
A356: 355 | B356: модульные | C356: unit/test_intents.py | E356: test_непроверяемое_условие_помечено_неизвестным | F356: Условие не про долг проверить нечем — часть не должна выполняться молча. | G356: 1
A357: 356 | B357: модульные | C357: unit/test_intents.py | E357: test_повторно_названная_задача_не_дублируется | F357: Повторно названная задача не дублируется | G357: 1
A358: 357 | B358: модульные | C358: unit/test_intents.py | E358: test_слова_связки_не_остаются_в_частях | F358: Слова связки не остаются в частях | G358: 1
A359: 358 | B359: модульные | C359: unit/test_intents.py | E359: test_признаки_фактов_счёта_совпадают_с_ответчиком | F359: Копия в детекторе не должна разойтись с оригиналом (import цикличен). | G359: 1
A360: 359 | B360: модульные | C360: unit/test_kb_build.py | E360: test_документ_с_персональными_данными_роняет_приём | F360: Ошибка, а не предупреждение. | G360: 3
A361: 360 | B361: модульные | C361: unit/test_kb_build.py | E361: test_ошибка_называет_документ_и_что_делать | F361: Сообщение читает человек, собирающий корпус, а не отладчик. | G361: 1
... A406: 405 | B406: модульные | C406: unit/test_kb_search.py | E406: test_настройка_доходит_до_загрузчика_модели | F406: Значение из настроек не должно потеряться по дороге: без этой проверки оно осталось бы объявленным и неподключённым — тот же класс ошибки, что с прогревом. | G406: 1
A407: 406 | B407: модульные | C407: unit/test_kb_search.py | E407: test_пустой_кэш_объясняет_себя_а_не_выглядит_отказом_сети | F407: Отказ из-за отсутствия весов в кэше неотличим от сетевой ошибки. | G407: 1 | H407: медленный (грузит языковую модель)
A408: 407 | B408: модульные | C408: unit/test_kb_search.py | E408: test_у_фрагмента_столько_векторов_сколько_частей | F408: Вопрос и части ответа — отдельные виды фрагмента, а не один склеенный. | G408: 1
A409: 408 | B409: модульные | C409: unit/test_kb_search.py | E409: test_близость_берётся_по_лучшей_части_а_не_по_средней | F409: Среднее вернуло бы то самое разбавление, ради устранения которого части и разведены. | G409: 1
A410: 409 | B410: модульные | C410: unit/test_kb_search.py | E410: test_в_промпт_уходит_пара_целиком_а_не_найденная_часть | F410: Единица поиска перестала совпадать с единицей контекста. | G410: 1
...

Sheet Файлы
A1: Уровень | B1: Файл | C1: О чём модуль | D1: Тестов (функций) | E1: Кейсов
A2: контрактные | B2: contract/test_api.py | C2: Проверки HTTP-интерфейса. | D2: =COUNTIF('Тесты'!$C$2:$C$718,B2) | E2: =SUMIF('Тесты'!$C$2:$C$718,B2,'Тесты'!$G$2:$G$718)
A3: контрактные | B3: contract/test_api_spec.py | C3: Проверки спецификации API. | D3: =COUNTIF('Тесты'!$C$2:$C$718,B3) | E3: =SUMIF('Тесты'!$C$2:$C$718,B3,'Тесты'!$G$2:$G$718)
A4: контрактные | B4: contract/test_llm_gateway.py | C4: Проверки шлюза к модели. | D4: =COUNTIF('Тесты'!$C$2:$C$718,B4) | E4: =SUMIF('Тесты'!$C$2:$C$718,B4,'Тесты'!$G$2:$G$718)
A5: контрактные | B5: contract/test_local_model_live.py | C5: Живая проверка на реальной модели. | D5: =COUNTIF('Тесты'!$C$2:$C$718,B5) | E5: =SUMIF('Тесты'!$C$2:$C$718,B5,'Тесты'!$G$2:$G$718)
A6: контрактные | B6: contract/test_orchestrator.py | C6: Проверки Backend: выбор пути ответа, поиск контекста, лимиты. | D6: =COUNTIF('Тесты'!$C$2:$C$718,B6) | E6: =SUMIF('Тесты'!$C$2:$C$718,B6,'Тесты'!$G$2:$G$718)
A7: контрактные | B7: contract/test_orchestrator_multi.py | C7: Backend: несколько задач в одной реплике — ответ на каждую часть. | D7: =COUNTIF('Тесты'!$C$2:$C$718,B7) | E7: =SUMIF('Тесты'!$C$2:$C$718,B7,'Тесты'!$G$2:$G$718)
A8: контрактные | B8: contract/test_provider_contract.py | C8: Контрактный тест провайдерского уровня. | D8: =COUNTIF('Тесты'!$C$2:$C$718,B8) | E8: =SUMIF('Тесты'!$C$2:$C$718,B8,'Тесты'!$G$2:$G$718)
A9: модульные | B9: unit/test_adapters.py | C9: Проверки адаптеров записи. | D9: =COUNTIF('Тесты'!$C$2:$C$718,B9) | E9: =SUMIF('Тесты'!$C$2:$C$718,B9,'Тесты'!$G$2:$G$718)
A10: модульные | B10: unit/test_agents.py | C10: Проверки агентов Этапа 1: классификатор и консультант. | D10: =COUNTIF('Тесты'!$C$2:$C$718,B10) | E10: =SUMIF('Тесты'!$C$2:$C$718,B10,'Тесты'!$G$2:$G$718)
A11: модульные | B11: unit/test_answer_judge.py | C11: Проверки судьи качества ответа (LLM-judge). | D11: =COUNTIF('Тесты'!$C$2:$C$718,B11) | E11: =SUMIF('Тесты'!$C$2:$C$718,B11,'Тесты'!$G$2:$G$718)
A12: модульные | B12: unit/test_billing_answer.py | C12: Проверки ответа о фактах лицевого счёта. | D12: =COUNTIF('Тесты'!$C$2:$C$718,B12) | E12: =SUMIF('Тесты'!$C$2:$C$718,B12,'Тесты'!$G$2:$G$718)
A13: модульные | B13: unit/test_billing_source.py | C13: Проверки доступа к данным Биллинга и личного кабинета. | D13: =COUNTIF('Тесты'!$C$2:$C$718,B13) | E13: =SUMIF('Тесты'!$C$2:$C$718,B13,'Тесты'!$G$2:$G$718)
... A53: модульные | B53: unit/test_usage_store.py | C53: Проверки хранилища событий использования (Postgres). | D53: =COUNTIF('Тесты'!$C$2:$C$718,B53) | E53: =SUMIF('Тесты'!$C$2:$C$718,B53,'Тесты'!$G$2:$G$718)
